Workbook

Sheet Loan_Data
A1: Customer_ID | B1: Customer_Name | C1: Father_Name | D1: Gender | E1: Age | F1: Marital_Status | G1: Occupation | H1: Education_Level | I1: Monthly_Income | J1: Employment_Type | K1: Years_of_Employment | L1: District | M1: Division | N1: Residential_Status | O1: Number_of_Dependents | P1: Branch_ID | Q1: Branch_Name | R1: Branch_City | S1: Branch_Division | T1: Loan_ID | U1: Loan_Type | V1: Loan_Amount | W1: Interest_Rate | X1: Loan_Term_Months | Y1: Application_Date | Z1: Approval_Date | AA1: Disbursement_Date | AB1: EMI_Amount | AC1: Collateral_Value | AD1: Existing_Loan_Count | AE1: Account_Balance | AF1: Savings_Amount | AG1: Monthly_Transaction_Count | AH1: Average_Monthly_Deposit | AI1: Credit_Score | AJ1: Debt_to_Income_Ratio | AK1: Risk_Level | AL1: Late_Payment_Count | AM1: Previous_Default | AN1: Repayment_Status | AO1: Loan_Status | AP1: Default_Probability
A2: BPBL-CUS-000001 | B2: Asaduzzaman Patwary | C2: Forhad Ahmed | D2: Male | E2: 43 | F2: Single | G2: Engineer | H2: Bachelor's | I2: 99000 | J2: Private | K2: 19 | L2: Feni | M2: Chattogram | N2: Own House | O2: 1 | P2: BR-11 | Q2: BPBL Kandirpar Branch | R2: Cumilla | S2: Chattogram | T2: BPBL-LN-2026-000001 | U2: Home Loan | V2: 4174000 | W2: 11.26 | X2: 258 | Y2: 46174 | Z2: 46183 | AA2: 46187 | AB2: =ROUND(PMT(W2/1200,X2,-V2),2) -> 43032.51 | AC2: 4617000 | AD2: 0 | AE2: 154900 | AF2: 56100 | AG2: 21 | AH2: 63900 | AI2: 759 | AJ2: =ROUND(AB2/I2,4) -> 0.4347 | AK2: =IF(AND(AI2>=750,AJ2<=0.35),"Low",IF(AND(AI2>=600,AJ2<=0.5),"Medium","High")) -> Medium | AL2: 1 | AM2: No | AN2: On Time | AO2: Approved | AP2: 0.165
A3: BPBL-CUS-000002 | B3: Aktar Akand | C3: Imran Gazi | D3: Male | E3: 46 | F3: Married | G3: Teacher | H3: Bachelor's | I3: 29500 | J3: Private | K3: 24 | L3: Kushtia | M3: Khulna | N3: Own House | O3: 0 | P3: BR-13 | Q3: BPBL M.K. Road Branch | R3: Jessore | S3: Khulna | T3: BPBL-LN-2026-000002 | U3: Business Loan | V3: 300000 | W3: 14.18 | X3: 54 | Y3: 46199 | Z3: 46207 | AA3: 46212 | AB3: =ROUND(PMT(W3/1200,X3,-V3),2) -> 7546.97 | AC3: 307000 | AD3: 0 | AE3: 21500 | AF3: 12400 | AG3: 33 | AH3: 31600 | AI3: 656 | AJ3: =ROUND(AB3/I3,4) -> 0.2558 | AK3: =IF(AND(AI3>=750,AJ3<=0.35),"Low",IF(AND(AI3>=600,AJ3<=0.5),"Medium","High")) -> Medium | AL3: 1 | AM3: No | AN3: On Time | AO3: Approved | AP3: 0.232
A4: BPBL-CUS-000003 | B4: Rezaul Patwary | C4: Riaz Rahman | D4: Male | E4: 31 | F4: Single | G4: Government Service | H4: HSC | I4: 47500 | J4: Government | K4: 9 | L4: Habiganj | M4: Sylhet | N4: Family Owned | O4: 0 | P4: BR-05 | Q4: BPBL Zindabazar Branch | R4: Sylhet | S4: Sylhet | T4: BPBL-LN-2026-000003 | U4: Agricultural Loan | V4: 116000 | W4: 10.2 | X4: 12 | Y4: 46188 | Z4: 46194 | AA4: 46196 | AB4: =ROUND(PMT(W4/1200,X4,-V4),2) -> 10209.04 | AC4: 0 | AD4: 1 | AF4: 41100 | AG4: 43 | AH4: 21300 | AI4: 710 | AJ4: =ROUND(AB4/I4,4) -> 0.2149 | AK4: =IF(AND(AI4>=750,AJ4<=0.35),"Low",IF(AND(AI4>=600,AJ4<=0.5),"Medium","High")) -> Medium | AM4: No | AN4: On Time | AO4: Closed | AP4: 0.164
A5: BPBL-CUS-000004 | B5: Bashir Das | C5: Monir Mondol | D5: Male | E5: 46 | F5: Married | G5: Retired | H5: HSC | I5: 28000 | J5: Retired | K5: 23 | L5: Tangail | M5: Dhaka | N5: Own House | O5: 0 | P5: BR-10 | Q5: BPBL Chashara Branch | R5: Narayanganj | S5: Dhaka | T5: BPBL-LN-2026-000004 | U5: Personal Loan | V5: 206000 | W5: 15.6 | X5: 30 | Y5: 46182 | Z5: 46192 | AA5: 46198 | AB5: =ROUND(PMT(W5/1200,X5,-V5),2) -> 8336.46 | AC5: 0 | AD5: 0 | AE5: 27800 | AG5: 3 | AH5: 10100 | AI5: 719 | AJ5: =ROUND(AB5/I5,4) -> 0.2977 | AK5: =IF(AND(AI5>=750,AJ5<=0.35),"Low",IF(AND(AI5>=600,AJ5<=0.5),"Medium","High")) -> Medium | AL5: 1 | AM5: No | AN5: On Time | AO5: Approved | AP5: 0.234
A6: BPBL-CUS-000005 | B6: Touhidul Sikder | C6: Mamunur Rahman | D6: Male | E6: 44 | F6: Married | G6: Engineer | H6: Master's | I6: 166500 | J6: Private | K6: 20 | L6: Khulna | M6: Khulna | N6: Staff Quarters | O6: 2 | P6: BR-03 | Q6: BPBL Sonadanga Branch | R6: Khulna | S6: Khulna | T6: BPBL-LN-2026-000005 | U6: Personal Loan | V6: 1500000 | W6: 13.27 | X6: 24 | Y6: 46198 | Z6: 46200 | AA6: 46202 | AB6: =ROUND(PMT(W6/1200,X6,-V6),2) -> 71503.11 | AC6: 0 | AD6: 0 | AE6: 600300 | AF6: 201800 | AG6: 46 | AH6: 65900 | AI6: 615 | AJ6: =ROUND(AB6/I6,4) -> 0.4294 | AK6: =IF(AND(AI6>=750,AJ6<=0.35),"Low",IF(AND(AI6>=600,AJ6<=0.5),"Medium","High")) -> Medium | AL6: 0 | AM6: No | AN6: On Time | AO6: Approved | AP6: 0.334
A7: BPBL-CUS-000006 | B7: Ferdousi Khan | C7: Wahidul Sardar | D7: Female | E7: 48 | F7: Single | G7: Housewife | H7: Below SSC | I7: 15000 | J7: Unemployed | K7: 20 | L7: Nilphamari | M7: Rangpur | N7: Family Owned | O7: 0 | P7: BR-07 | Q7: BPBL Jahaj Company Mor Branch | R7: Rangpur | S7: Rangpur | T7: BPBL-LN-2026-000006 | U7: Education Loan | V7: 100000 | W7: 8.41 | X7: 12 | Y7: 46179 | Z7: 46184 | AA7: 46189 | AB7: =ROUND(PMT(W7/1200,X7,-V7),2) -> 8717.81 | AC7: 0 | AD7: 1 | AE7: 34200 | AF7: 18900 | AG7: 42 | AH7: 7500 | AI7: 467 | AJ7: =ROUND(AB7/I7,4) -> 0.5812 | AK7: =IF(AND(AI7>=750,AJ7<=0.35),"Low",IF(AND(AI7>=600,AJ7<=0.5),"Medium","High")) -> High | AL7: 0 | AM7: No | AN7: Delayed | AO7: Approved | AP7: 0.38
A8: BPBL-CUS-000007 | B8: Aminul Islam | C8: Aminul Faruqui | D8: Male | E8: 54 | F8: Married | G8: Retired | H8: SSC | I8: 20000 | J8: Retired | K8: 28 | L8: Narayanganj | M8: Dhaka | O8: 1 | P8: BR-14 | Q8: BPBL Victoria Road Branch | R8: Tangail | S8: Dhaka | T8: BPBL-LN-2026-000007 | U8: Agricultural Loan | V8: 195000 | W8: 10.01 | X8: 24 | Y8: 46200 | AB8: =ROUND(PMT(W8/1200,X8,-V8),2) -> 8999.16 | AC8: 0 | AD8: 0 | AE8: 26000 | AF8: 8200 | AH8: 19100 | AI8: 769 | AJ8: =ROUND(AB8/I8,4) -> 0.45 | AK8: =IF(AND(AI8>=750,AJ8<=0.35),"Low",IF(AND(AI8>=600,AJ8<=0.5),"Medium","High")) -> Medium | AL8: 2 | AM8: No | AO8: Rejected | AP8: 0.161
A9: BPBL-CUS-000008 | B9: Anika Mia | C9: Masud Sardar | D9: Female | E9: 21 | F9: Married | G9: Housewife | H9: Bachelor's | I9: 19000 | J9: Unemployed | K9: 0 | L9: Cumilla | M9: Chattogram | N9: Own House | O9: 1 | P9: BR-02 | Q9: BPBL Agrabad Branch | R9: Chattogram | S9: Chattogram | T9: BPBL-LN-2026-000008 | U9: Business Loan | V9: 359000 | W9: 16.38 | X9: 84 | Y9: 46180 | AB9: =ROUND(PMT(W9/1200,X9,-V9),2) -> 7208.4 | AC9: 404000 | AD9: 0 | AE9: 28400 | AF9: 3400 | AG9: 27 | AH9: 15000 | AI9: 691 | AJ9: =ROUND(AB9/I9,4) -> 0.3794 | AK9: =IF(AND(AI9>=750,AJ9<=0.35),"Low",IF(AND(AI9>=600,AJ9<=0.5),"Medium","High")) -> Medium | AL9: 2 | AM9: No | AO9: Pending | AP9: 0.183
A10: BPBL-CUS-000009 | B10: Shirin Patwary | C10: Nurul Das | D10: Female | E10: 30 | F10: Married | G10: Government Service | H10: HSC | I10: 33000 | J10: Government | K10: 3 | L10: Pirojpur | M10: Barishal | N10: Rented House | O10: 2 | P10: BR-07 | Q10: BPBL Jahaj Company Mor Branch | R10: Rangpur | S10: Rangpur | T10: BPBL-LN-2026-000009 | U10: Personal Loan | V10: 389000 | W10: 14.78 | X10: 48 | Y10: 46175 | Z10: 46176 | AA10: 46179 | AB10: =ROUND(PMT(W10/1200,X10,-V10),2) -> 10782.83 | AC10: 0 | AD10: 0 | AE10: 59000 | AF10: 24600 | AG10: 15 | AH10: 26600 | AI10: 734 | AJ10: =ROUND(AB10/I10,4) -> 0.3268 | AK10: =IF(AND(AI10>=750,AJ10<=0.35),"Low",IF(AND(AI10>=600,AJ10<=0.5),"Medium","High")) -> Medium | AL10: 0 | AM10: No | AN10: On Time | AO10: Approved | AP10: 0.224
A11: BPBL-CUS-000010 | B11: Ashraf Khan | C11: Aminul Mia | D11: Male | E11: 28 | F11: Married | G11: Self-Employed | H11: Below SSC | I11: 23500 | J11: Self-Employed | K11: 6 | L11: Chapainawabganj | M11: Rajshahi | N11: Own House | O11: 2 | P11: BR-04 | Q11: BPBL Shaheb Bazar Branch | R11: Rajshahi | S11: Rajshahi | T11: BPBL-LN-2026-000010 | U11: Education Loan | V11: 254000 | W11: 8.63 | X11: 30 | Y11: 46175 | Z11: 46177 | AA11: 46178 | AB11: =ROUND(PMT(W11/1200,X11,-V11),2) -> 9443.12 | AC11: 0 | AD11: 0 | AE11: 68600 | AF11: 20100 | AG11: 34 | AH11: 24700 | AI11: 861 | AJ11: =ROUND(AB11/I11,4) -> 0.4018 | AK11: =IF(AND(AI11>=750,AJ11<=0.35),"Low",IF(AND(AI11>=600,AJ11<=0.5),"Medium","High")) -> Medium | AL11: 0 | AM11: No | AN11: On Time | AO11: Closed | AP11: 0.033
A12: BPBL-CUS-000011 | B12: Tariqul Sheikh | C12: Mizanur Miah | D12: Male | E12: 33 | F12: Married | G12: Freelancer | I12: 23000 | J12: Self-Employed | K12: 8 | L12: Rajshahi | M12: Rajshahi | N12: Own House | O12: 0 | P12: BR-04 | Q12: BPBL Shaheb Bazar Branch | R12: Rajshahi | S12: Rajshahi | T12: BPBL-LN-2026-000011 | U12: Agricultural Loan | V12: 51000 | W12: 8.01 | X12: 6 | Y12: 46176 | AB12: =ROUND(PMT(W12/1200,X12,-V12),2) -> 8699.68 | AC12: 0 | AD12: 2 | AE12: 39600 | AF12: 18300 | AG12: 44 | AH12: 23400 | AI12: 786 | AJ12: =ROUND(AB12/I12,4) -> 0.3782 | AK12: =IF(AND(AI12>=750,AJ12<=0.35),"Low",IF(AND(AI12>=600,AJ12<=0.5),"Medium","High")) -> Medium | AM12: No | AO12: Pending | AP12: 0.101
A13: BPBL-CUS-000012 | B13: Habibur Mia | C13: Delwar Talukder | D13: Male | E13: 40 | F13: Married | G13: Self-Employed | I13: 54500 | J13: Self-Employed | K13: 15 | L13: Mymensingh | M13: Mymensingh | N13: Rented House | O13: 1 | P13: BR-08 | Q13: BPBL Notun Bazar Branch | R13: Mymensingh | S13: Mymensingh | T13: BPBL-LN-2026-000012 | U13: Business Loan | V13: 1026000 | W13: 11.87 | X13: 60 | Y13: 46195 | AB13: =ROUND(PMT(W13/1200,X13,-V13),2) -> 22755.46 | AC13: 1029000 | AD13: 0 | AE13: 159200 | AF13: 67800 | AG13: 10 | AH13: 26100 | AI13: 753 | AJ13: =ROUND(AB13/I13,4) -> 0.4175 | AK13: =IF(AND(AI13>=750,AJ13<=0.35),"Low",IF(AND(AI13>=600,AJ13<=0.5),"Medium","High")) -> Medium | AL13: 0 | AM13: No | AO13: Rejected | AP13: 0.182
A14: BPBL-CUS-000013 | B14: Yeasin Faruqui | C14: Aminul Hossain | D14: Male | E14: 68 | F14: Married | G14: Doctor | H14: PhD | I14: 239500 | J14: Self-Employed | K14: 7 | L14: Munshiganj | M14: Dhaka | N14: Staff Quarters | O14: 2 | P14: BR-01 | Q14: BPBL Gulshan Branch | R14: Dhaka | S14: Dhaka | T14: BPBL-LN-2026-000013 | U14: Personal Loan | V14: 1500000 | W14: 12.7 | X14: 60 | Y14: 46193 | Z14: 46197 | AA14: 46201 | AB14: =ROUND(PMT(W14/1200,X14,-V14),2) -> 33899.69 | AC14: 0 | AD14: 2 | AE14: 648800 | AF14: 322700 | AG14: 24 | AH14: 168200 | AI14: 707 | AJ14: =ROUND(AB14/I14,4) -> 0.1415 | AK14: =IF(AND(AI14>=750,AJ14<=0.35),"Low",IF(AND(AI14>=600,AJ14<=0.5),"Medium","High")) -> Medium | AL14: 0 | AM14: No | AN14: On Time | AO14: Approved | AP14: 0.252
A15: BPBL-CUS-000014 | B15: Iqbal Khan | C15: Mahmudul Hawlader | D15: Male | E15: 35 | F15: Widowed | G15: Business Owner | H15: Bachelor's | I15: 182000 | J15: Business | K15: 11 | L15: Kishoreganj | M15: Dhaka | N15: Own House | O15: 0 | P15: BR-10 | Q15: BPBL Chashara Branch | R15: Narayanganj | S15: Dhaka | T15: BPBL-LN-2026-000014 | U15: Car Loan | V15: 2788000 | W15: 13.11 | X15: 72 | Y15: 46188 | Z15: 46190 | AA15: 46191 | AB15: =ROUND(PMT(W15/1200,X15,-V15),2) -> 56128.6 | AC15: 4063000 | AD15: 1 | AE15: 706800 | AF15: 411200 | AG15: 38 | AH15: 178800 | AI15: 759 | AJ15: =ROUND(AB15/I15,4) -> 0.3084 | AK15: =IF(AND(AI15>=750,AJ15<=0.35),"Low",IF(AND(AI15>=600,AJ15<=0.5),"Medium","High")) -> Low | AL15: 0 | AM15: No | AN15: On Time | AO15: Approved | AP15: 0.164
A16: BPBL-CUS-000015 | B16: Shafin Gazi | C16: Mostafa Khan | D16: Male | E16: 28 | F16: Married | G16: Business Owner | H16: HSC | I16: 37000 | J16: Business | K16: 5 | L16: Rajshahi | M16: Rajshahi | N16: Family Owned | O16: 2 | P16: BR-04 | Q16: BPBL Shaheb Bazar Branch | R16: Rajshahi | S16: Rajshahi | T16: BPBL-LN-2026-000015 | U16: Business Loan | V16: 654000 | W16: 14.35 | X16: 72 | Y16: 46199 | AB16: =ROUND(PMT(W16/1200,X16,-V16),2) -> 13599.03 | AC16: 896000 | AD16: 2 | AE16: 65100 | AG16: 42 | AH16: 35100 | AI16: 596 | AJ16: =ROUND(AB16/I16,4) -> 0.3675 | AK16: =IF(AND(AI16>=750,AJ16<=0.35),"Low",IF(AND(AI16>=600,AJ16<=0.5),"Medium","High")) -> High | AL16: 2 | AM16: No | AO16: Rejected | AP16: 0.391
A17: BPBL-CUS-000016 | B17: Shafiqul Patwary | C17: Mehedi Ahmed | D17: Male | E17: 41 | F17: Married | G17: Business Owner | H17: Bachelor's | I17: 94500 | J17: Business | K17: 18 | L17: Noakhali | M17: Chattogram | N17: Own House | O17: 3 | P17: BR-15 | Q17: BPBL Maijdee Court Branch | R17: Noakhali | S17: Chattogram | T17: BPBL-LN-2026-000016 | U17: SME Loan | V17: 534000 | W17: 11.88 | X17: 18 | Y17: 46189 | Z17: 46190 | AA17: 46191 | AB17: =ROUND(PMT(W17/1200,X17,-V17),2) -> 32534.65 | AC17: 688000 | AD17: 1 | AE17: 226700 | AF17: 55100 | AG17: 20 | AI17: 750 | AJ17: =ROUND(AB17/I17,4) -> 0.3443 | AK17: =IF(AND(AI17>=750,AJ17<=0.35),"Low",IF(AND(AI17>=600,AJ17<=0.5),"Medium","High")) -> Low | AL17: 0 | AM17: No | AN17: On Time | AO17: Approved | AP17: 0.176
A18: BPBL-CUS-000017 | B18: Shamim Karim | C18: Mehedi Sardar | D18: Male | E18: 32 | H18: PhD | I18: 287000 | J18: Self-Employed | K18: 14 | L18: Patuakhali | M18: Barishal | N18: Own House | O18: 0 | P18: BR-06 | Q18: BPBL Sadar Road Branch | R18: Barishal | S18: Barishal | T18: BPBL-LN-2026-000017 | U18: Agricultural Loan | V18: 800000 | W18: 7.38 | X18: 24 | Y18: 46191 | Z18: 46197 | AA18: 46202 | AB18: =ROUND(PMT(W18/1200,X18,-V18),2) -> 35956.04 | AC18: 0 | AD18: 1 | AE18: 872900 | AF18: 513200 | AG18: 36 | AH18: 204600 | AI18: 811 | AJ18: =ROUND(AB18/I18,4) -> 0.1253 | AK18: =IF(AND(AI18>=750,AJ18<=0.35),"Low",IF(AND(AI18>=600,AJ18<=0.5),"Medium","High")) -> Low | AL18: 0 | AM18: No | AN18: On Time | AO18: Approved | AP18: 0.207
A19: BPBL-CUS-000018 | B19: Yeasin Miah | C19: Tanvir Sarkar | D19: Male | E19: 49 | F19: Married | G19: Government Service | H19: Master's | I19: 55000 | J19: Government | K19: 24 | L19: Munshiganj | M19: Dhaka | O19: 1 | P19: BR-06 | Q19: BPBL Sadar Road Branch | R19: Barishal | S19: Barishal | T19: BPBL-LN-2026-000018 | U19: Home Loan | V19: 1566000 | W19: 8.8 | X19: 96 | Y19: 46199 | AB19: =ROUND(PMT(W19/1200,X19,-V19),2) -> 22780.07 | AC19: 1762000 | AD19: 0 | AE19: 154600 | AF19: 37100 | AG19: 33 | AH19: 58500 | AI19: 786 | AJ19: =ROUND(AB19/I19,4) -> 0.4142 | AK19: =IF(AND(AI19>=750,AJ19<=0.35),"Low",IF(AND(AI19>=600,AJ19<=0.5),"Medium","High")) -> Medium | AL19: 0 | AM19: No | AO19: Rejected | AP19: 0.215
A20: BPBL-CUS-000019 | B20: Nazrul Mollah | C20: Tanvir Mia | D20: Male | E20: 42 | F20: Single | G20: Private Service | H20: HSC | I20: 73500 | J20: Private | K20: 16 | L20: Lalmonirhat | M20: Rangpur | N20: Own House | O20: 0 | P20: BR-12 | Q20: BPBL Satmatha Branch | R20: Bogura | S20: Rajshahi | T20: BPBL-LN-2026-000019 | U20: Agricultural Loan | V20: 85000 | W20: 7.92 | X20: 6 | Y20: 46200 | AB20: =ROUND(PMT(W20/1200,X20,-V20),2) -> 14495.71 | AC20: 0 | AD20: 0 | AE20: 61900 | AF20: 21400 | AG20: 54 | AH20: 49900 | AI20: 670 | AJ20: =ROUND(AB20/I20,4) -> 0.1972 | AK20: =IF(AND(AI20>=750,AJ20<=0.35),"Low",IF(AND(AI20>=600,AJ20<=0.5),"Medium","High")) -> Medium | AL20: 1 | AM20: No | AO20: Rejected | AP20: 0.256
A21: BPBL-CUS-000020 | B21: Touhidul Pramanik | C21: Shamim Roy | D21: Male | E21: 35 | G21: Doctor | H21: PhD | I21: 139000 | J21: Self-Employed | K21: 12 | L21: Nilphamari | M21: Rangpur | N21: Own House | O21: 2 | P21: BR-07 | Q21: BPBL Jahaj Company Mor Branch | R21: Rangpur | S21: Rangpur | T21: BPBL-LN-2026-000020 | U21: Agricultural Loan | V21: 449000 | W21: 9.66 | X21: 24 | Y21: 46182 | Z21: 46192 | AA21: 46196 | AB21: =ROUND(PMT(W21/1200,X21,-V21),2) -> 20648.68 | AC21: 0 | AD21: 0 | AE21: 354500 | AF21: 202100 | AG21: 28 | AH21: 105700 | AI21: 862 | AJ21: =ROUND(AB21/I21,4) -> 0.1486 | AK21: =IF(AND(AI21>=750,AJ21<=0.35),"Low",IF(AND(AI21>=600,AJ21<=0.5),"Medium","High")) -> Low | AL21: 0 | AM21: No | AN21: On Time | AO21: Approved | AP21: 0.067
A22: BPBL-CUS-000021 | B22: Hossain Sardar | C22: Nurul Miah | D22: Male | E22: 55 | F22: Married | G22: Doctor | H22: PhD | I22: 171000 | J22: Self-Employed | K22: 32 | L22: Cox's Bazar | M22: Chattogram | N22: Rented House | O22: 3 | P22: BR-02 | Q22: BPBL Agrabad Branch | R22: Chattogram | S22: Chattogram | T22: BPBL-LN-2026-000021 | U22: Agricultural Loan | V22: 699000 | W22: 9.99 | X22: 12 | Y22: 46193 | Z22: 46195 | AA22: 46201 | AB22: =ROUND(PMT(W22/1200,X22,-V22),2) -> 61449.95 | AC22: 0 | AD22: 2 | AE22: 461900 | AF22: 248800 | AG22: 18 | AH22: 151900 | AI22: 681 | AJ22: =ROUND(AB22/I22,4) -> 0.3594 | AK22: =IF(AND(AI22>=750,AJ22<=0.35),"Low",IF(AND(AI22>=600,AJ22<=0.5),"Medium","High")) -> Medium | AL22: 2 | AM22: No | AN22: Delayed | AO22: Approved | AP22: 0.284
A23: BPBL-CUS-000022 | B23: Nayeem Majumder | C23: Towhid Talukder | D23: Male | E23: 31 | F23: Married | G23: Retired | H23: HSC | I23: 28000 | J23: Retired | K23: 6 | L23: Barishal | M23: Barishal | N23: Rented House | O23: 0 | P23: BR-06 | Q23: BPBL Sadar Road Branch | R23: Barishal | S23: Barishal | T23: BPBL-LN-2026-000022 | U23: Personal Loan | V23: 269000 | W23: 15.88 | X23: 54 | Y23: 46187 | Z23: 46197 | AA23: 46203 | AB23: =ROUND(PMT(W23/1200,X23,-V23),2) -> 7003.1 | AC23: 0 | AD23: 3 | AE23: 87900 | AF23: 13300 | AG23: 21 | AH23: 28600 | AI23: 811 | AJ23: =ROUND(AB23/I23,4) -> 0.2501 | AK23: =IF(AND(AI23>=750,AJ23<=0.35),"Low",IF(AND(AI23>=600,AJ23<=0.5),"Medium","High")) -> Low | AL23: 0 | AM23: No | AN23: On Time | AO23: Closed | AP23: 0.184
A24: BPBL-CUS-000023 | B24: Shapla Rahman | C24: Ataur Miah | D24: Female | E24: 52 | F24: Married | G24: Engineer | H24: Bachelor's | I24: 116000 | J24: Private | K24: 29 | L24: Narayanganj | M24: Dhaka | N24: Own House | O24: 2 | P24: BR-09 | Q24: BPBL Chandona Chowrasta Branch | R24: Gazipur | S24: Dhaka | T24: BPBL-LN-2026-000023 | U24: Home Loan | V24: 3767000 | W24: 9.31 | X24: 222 | Y24: 46181 | AB24: =ROUND(PMT(W24/1200,X24,-V24),2) -> 35633.95 | AC24: 5184000 | AD24: 0 | AE24: 95000 | AF24: 33000 | AG24: 36 | AH24: 40100 | AI24: 771 | AJ24: =ROUND(AB24/I24,4) -> 0.3072 | AK24: =IF(AND(AI24>=750,AJ24<=0.35),"Low",IF(AND(AI24>=600,AJ24<=0.5),"Medium","High")) -> Low | AL24: 4 | AM24: Yes | AO24: Pending | AP24: 0.34
A25: BPBL-CUS-000024 | B25: Borsha Mondol | C25: Nurul Sarker | D25: Female | E25: 21 | F25: Married | G25: Engineer | H25: Bachelor's | I25: 137000 | J25: Private | K25: 0 | L25: Noakhali | M25: Chattogram | N25: Own House | O25: 2 | P25: BR-15 | Q25: BPBL Maijdee Court Branch | R25: Noakhali | S25: Chattogram | T25: BPBL-LN-2026-000024 | U25: SME Loan | V25: 2981000 | W25: 10.63 | X25: 60 | Y25: 46188 | Z25: 46192 | AA25: 46193 | AB25: =ROUND(PMT(W25/1200,X25,-V25),2) -> 64265.46 | AC25: 3089000 | AD25: 0 | AE25: 107500 | AF25: 15300 | AG25: 40 | AH25: 149200 | AI25: 782 | AJ25: =ROUND(AB25/I25,4) -> 0.4691 | AK25: =IF(AND(AI25>=750,AJ25<=0.35),"Low",IF(AND(AI25>=600,AJ25<=0.5),"Medium","High")) -> Medium | AL25: 0 | AM25: No | AN25: On Time | AO25: Approved | AP25: 0.171
A26: BPBL-CUS-000025 | B26: Rokeya Sarker | C26: Hasan Sheikh | D26: Female | E26: 22 | F26: Single | G26: Freelancer | H26: Master's | I26: 27500 | J26: Self-Employed | K26: 0 | L26: Faridpur | M26: Dhaka | N26: Rented House | O26: 3 | P26: BR-09 | Q26: BPBL Chandona Chowrasta Branch | R26: Gazipur | S26: Dhaka | T26: BPBL-LN-2026-000025 | U26: Education Loan | V26: 607000 | W26: 8.02 | X26: 48 | Y26: 46181 | AB26: =ROUND(PMT(W26/1200,X26,-V26),2) -> 14824.34 | AC26: 0 | AE26: 85600 | AF26: 33500 | AG26: 16 | AH26: 29400 | AI26: 504 | AJ26: =ROUND(AB26/I26,4) -> 0.5391 | AK26: =IF(AND(AI26>=750,AJ26<=0.35),"Low",IF(AND(AI26>=600,AJ26<=0.5),"Medium","High")) -> High | AL26: 2 | AM26: No | AO26: Rejected | AP26: 0.444
A27: BPBL-CUS-000026 | B27: Rezaul Miah | C27: Zahirul Hasan | D27: Male | E27: 22 | F27: Married | G27: Farmer | I27: 8500 | J27: Self-Employed | K27: 1 | L27: Moulvibazar | M27: Sylhet | N27: Own House | O27: 1 | P27: BR-05 | Q27: BPBL Zindabazar Branch | R27: Sylhet | S27: Sylhet | T27: BPBL-LN-2026-000026 | U27: Education Loan | V27: 233000 | W27: 9.2 | X27: 84 | Y27: 46187 | Z27: 46196 | AA27: 46200 | AB27: =ROUND(PMT(W27/1200,X27,-V27),2) -> 3772.45 | AC27: 0 | AD27: 1 | AE27: 24900 | AF27: 8100 | AG27: 33 | AH27: 6800 | AI27: 686 | AJ27: =ROUND(AB27/I27,4) -> 0.4438 | AK27: =IF(AND(AI27>=750,AJ27<=0.35),"Low",IF(AND(AI27>=600,AJ27<=0.5),"Medium","High")) -> Medium | AM27: No | AN27: On Time | AO27: Approved | AP27: 0.341
A28: BPBL-CUS-000027 | B28: Ataur Karim | C28: Jasim Hawlader | D28: Male | E28: 47 | F28: Married | G28: Engineer | H28: Master's | I28: 134500 | J28: Private | K28: 20 | L28: Gaibandha | M28: Rangpur | N28: Rented House | O28: 0 | P28: BR-14 | Q28: BPBL Victoria Road Branch | R28: Tangail | S28: Dhaka | T28: BPBL-LN-2026-000027 | U28: Home Loan | V28: 2774000 | W28: 8.56 | X28: 168 | Y28: 46186 | Z28: 46193 | AA28: 46199 | AB28: =ROUND(PMT(W28/1200,X28,-V28),2) -> 28388.53 | AC28: 3264000 | AD28: 0 | AF28: 311900 | AG28: 30 | AH28: 115500 | AI28: 900 | AJ28: =ROUND(AB28/I28,4) -> 0.2111 | AK28: =IF(AND(AI28>=750,AJ28<=0.35),"Low",IF(AND(AI28>=600,AJ28<=0.5),"Medium","High")) -> Low | AL28: 0 | AM28: No | AN28: On Time | AO28: Approved | AP28: 0.01
A29: BPBL-CUS-000028 | B29: Liton Hasan | C29: Quamrul Hawlader | D29: Male | E29: 21 | F29: Single | G29: Private Service | H29: Bachelor's | I29: 51500 | J29: Private | K29: 0 | L29: Dhaka | M29: Dhaka | N29: Own House | O29: 1 | P29: BR-01 | Q29: BPBL Gulshan Branch | R29: Dhaka | S29: Dhaka | T29: BPBL-LN-2026-000028 | U29: Car Loan | V29: 887000 | W29: 9.9 | X29: 36 | Y29: 46186 | Z29: 46193 | AA29: 46196 | AB29: =ROUND(PMT(W29/1200,X29,-V29),2) -> 28579.37 | AC29: 1246000 | AD29: 0 | AE29: 200600 | AF29: 104500 | AG29: 46 | AH29: 50000 | AI29: 581 | AJ29: =ROUND(AB29/I29,4) -> 0.5549 | AK29: =IF(AND(AI29>=750,AJ29<=0.35),"Low",IF(AND(AI29>=600,AJ29<=0.5),"Medium","High")) -> High | AL29: 2 | AM29: No | AN29: Missed Payment | AO29: Approved | AP29: 0.292
A30: BPBL-CUS-000029 | B30: Promi Munshi | C30: Mizanur Chowdhury | D30: Female | E30: 21 | F30: Single | G30: Engineer | H30: Bachelor's | I30: 61500 | J30: Private | K30: 0 | L30: Bhola | M30: Barishal | N30: Rented House | O30: 0 | P30: BR-01 | Q30: BPBL Gulshan Branch | R30: Dhaka | S30: Dhaka | T30: BPBL-LN-2026-000029 | U30: Car Loan | V30: 368000 | W30: 11.25 | X30: 18 | Y30: 46177 | Z30: 46181 | AA30: 46185 | AB30: =ROUND(PMT(W30/1200,X30,-V30),2) -> 22313.4 | AC30: 544000 | AD30: 0 | AE30: 175300 | AF30: 71700 | AG30: 35 | AH30: 36100 | AI30: 721 | AJ30: =ROUND(AB30/I30,4) -> 0.3628 | AK30: =IF(AND(AI30>=750,AJ30<=0.35),"Low",IF(AND(AI30>=600,AJ30<=0.5),"Medium","High")) -> Medium | AL30: 6 | AM30: No | AN30: Delayed | AO30: Approved | AP30: 0.235
A31: BPBL-CUS-000030 | B31: Kamal Faruqui | C31: Touhidul Hossain | D31: Male | E31: 41 | F31: Widowed | G31: Engineer | H31: Master's | I31: 97000 | J31: Private | K31: 16 | L31: Jessore | M31: Khulna | N31: Own House | O31: 0 | P31: BR-13 | Q31: BPBL M.K. Road Branch | R31: Jessore | S31: Khulna | T31: BPBL-LN-2026-000030 | U31: SME Loan | V31: 499000 | W31: 10.95 | X31: 12 | Y31: 46177 | Z31: 46182 | AA31: 46188 | AB31: =ROUND(PMT(W31/1200,X31,-V31),2) -> 44090.81 | AC31: 687000 | AD31: 1 | AE31: 120800 | AF31: 20300 | AG31: 40 | AH31: 30200 | AI31: 736 | AJ31: =ROUND(AB31/I31,4) -> 0.4545 | AK31: =IF(AND(AI31>=750,AJ31<=0.35),"Low",IF(AND(AI31>=600,AJ31<=0.5),"Medium","High")) -> Medium | AL31: 2 | AM31: No | AN31: On Time | AO31: Closed | AP31: 0.278
A32: BPBL-CUS-000031 | B32: Bashir Patwary | C32: Jasim Hawlader | D32: Male | E32: 49 | F32: Married | G32: Freelancer | H32: Bachelor's | I32: 28500 | J32: Self-Employed | K32: 27 | L32: Barishal | M32: Barishal | N32: Staff Quarters | O32: 1 | P32: BR-06 | Q32: BPBL Sadar Road Branch | R32: Barishal | S32: Barishal | T32: BPBL-LN-2026-000031 | U32: SME Loan | V32: 452000 | W32: 12.6 | X32: 72 | Y32: 46196 | Z32: 46199 | AA32: 46205 | AB32: =ROUND(PMT(W32/1200,X32,-V32),2) -> 8978.35 | AC32: 667000 | AD32: 1 | AE32: 60000 | AF32: 35400 | AG32: 27 | AH32: 19800 | AI32: 857 | AJ32: =ROUND(AB32/I32,4) -> 0.315 | AK32: =IF(AND(AI32>=750,AJ32<=0.35),"Low",IF(AND(AI32>=600,AJ32<=0.5),"Medium","High")) -> Low | AL32: 0 | AM32: No | AN32: On Time | AO32: Approved | AP32: 0.011
A33: BPBL-CUS-000032 | B33: Sohel Bhuiyan | C33: Ashraf Patwary | D33: Male | E33: 50 | F33: Married | G33: Retired | H33: Bachelor's | I33: 22500 | J33: Retired | K33: 24 | L33: Jhenaidah | M33: Khulna | N33: Family Owned | O33: 1 | P33: BR-13 | Q33: BPBL M.K. Road Branch | R33: Jessore | S33: Khulna | T33: BPBL-LN-2026-000032 | U33: Business Loan | V33: 300000 | W33: 13.08 | X33: 78 | Y33: 46184 | Z33: 46190 | AA33: 46192 | AB33: =ROUND(PMT(W33/1200,X33,-V33),2) -> 5729.8 | AC33: 371000 | AD33: 0 | AE33: 26400 | AF33: 3200 | AG33: 35 | AH33: 9800 | AI33: 759 | AJ33: =ROUND(AB33/I33,4) -> 0.2547 | AK33: =IF(AND(AI33>=750,AJ33<=0.35),"Low",IF(AND(AI33>=600,AJ33<=0.5),"Medium","High")) -> Low | AL33: 0 | AM33: No | AN33: On Time | AO33: Approved | AP33: 0.13
A34: BPBL-CUS-000033 | B34: Monir Sheikh | C34: Mostafa Munshi | D34: Male | E34: 29 | F34: Widowed | G34: Private Service | H34: Master's | I34: 49000 | J34: Private | K34: 2 | L34: Khagrachari | M34: Chattogram | N34: Rented House | O34: 0 | P34: BR-15 | Q34: BPBL Maijdee Court Branch | R34: Noakhali | S34: Chattogram | T34: BPBL-LN-2026-000033 | U34: Car Loan | V34: 609000 | W34: 13.02 | X34: 48 | Y34: 46196 | Z34: 46197 | AA34: 46198 | AB34: =ROUND(PMT(W34/1200,X34,-V34),2) -> 16343.99 | AC34: 634000 | AD34: 0 | AE34: 162800 | AF34: 77200 | AG34: 24 | AH34: 21900 | AI34: 571 | AJ34: =ROUND(AB34/I34,4) -> 0.3336 | AK34: =IF(AND(AI34>=750,AJ34<=0.35),"Low",IF(AND(AI34>=600,AJ34<=0.5),"Medium","High")) -> High | AL34: 3 | AM34: No | AN34: On Time | AO34: Approved | AP34: 0.38
A35: BPBL-CUS-000034 | B35: Sathi Sarkar | C35: Anisur Talukder | D35: Female | E35: 31 | F35: Married | G35: Farmer | H35: SSC | I35: 10500 | J35: Self-Employed | K35: 8 | L35: Mymensingh | M35: Mymensingh | N35: Own House | O35: 2 | P35: BR-08 | Q35: BPBL Notun Bazar Branch | R35: Mymensingh | S35: Mymensingh | T35: BPBL-LN-2026-000034 | U35: Car Loan | V35: 300000 | W35: 9.73 | X35: 36 | Y35: 46191 | AB35: =ROUND(PMT(W35/1200,X35,-V35),2) -> 9642.17 | AC35: 380000 | AD35: 0 | AE35: 19100 | AF35: 2100 | AG35: 15 | AH35: 5900 | AI35: 780 | AJ35: =ROUND(AB35/I35,4) -> 0.9183 | AK35: =IF(AND(AI35>=750,AJ35<=0.35),"Low",IF(AND(AI35>=600,AJ35<=0.5),"Medium","High")) -> High | AL35: 2 | AM35: No | AO35: Pending | AP35: 0.146
A36: BPBL-CUS-000035 | B36: Eti Das | C36: Arif Ahmed | D36: Female | E36: 30 | F36: Single | G36: Self-Employed | H36: HSC | I36: 26500 | J36: Self-Employed | K36: 11 | L36: Natore | M36: Rajshahi | N36: Own House | O36: 0 | P36: BR-12 | Q36: BPBL Satmatha Branch | R36: Bogura | S36: Rajshahi | T36: BPBL-LN-2026-000035 | U36: Agricultural Loan | V36: 288000 | W36: 9.14 | X36: 24 | Y36: 46196 | AB36: =ROUND(PMT(W36/1200,X36,-V36),2) -> 13175.71 | AC36: 0 | AD36: 2 | AE36: 25100 | AG36: 50 | AH36: 15600 | AI36: 690 | AJ36: =ROUND(AB36/I36,4) -> 0.4972 | AK36: =IF(AND(AI36>=750,AJ36<=0.35),"Low",IF(AND(AI36>=600,AJ36<=0.5),"Medium","High")) -> Medium | AL36: 0 | AM36: No | AO36: Pending | AP36: 0.215
A37: BPBL-CUS-000036 | B37: Aminul Chowdhury | C37: Golam Miah | D37: Male | E37: 48 | F37: Married | H37: Master's | I37: 78500 | J37: Retired | K37: 29 | L37: Munshiganj | M37: Dhaka | N37: Own House | O37: 3 | P37: BR-10 | Q37: BPBL Chashara Branch | R37: Narayanganj | S37: Dhaka | T37: BPBL-LN-2026-000036 | U37: Personal Loan | V37: 431000 | W37: 12.36 | X37: 24 | Y37: 46175 | Z37: 46185 | AA37: 46188 | AB37: =ROUND(PMT(W37/1200,X37,-V37),2) -> 20361.2 | AC37: 0 | AD37: 0 | AE37: 152000 | AF37: 89900 | AG37: 16 | AH37: 30600 | AI37: 730 | AJ37: =ROUND(AB37/I37,4) -> 0.2594 | AK37: =IF(AND(AI37>=750,AJ37<=0.35),"Low",IF(AND(AI37>=600,AJ37<=0.5),"Medium","High")) -> Medium | AL37: 0 | AM37: No | AN37: On Time | AO37: Approved | AP37: 0.198
A38: BPBL-CUS-000037 | B38: Aminul Sarkar | C38: Golam Rahman | D38: Male | E38: 42 | F38: Widowed | G38: Self-Employed | H38: Bachelor's | I38: 51000 | J38: Self-Employed | K38: 20 | L38: Madaripur | M38: Dhaka | N38: Rented House | O38: 2 | P38: BR-10 | Q38: BPBL Chashara Branch | R38: Narayanganj | S38: Dhaka | T38: BPBL-LN-2026-000037 | U38: Agricultural Loan | V38: 472000 | W38: 8.13 | X38: 30 | Y38: 46180 | Z38: 46185 | AA38: 46191 | AB38: =ROUND(PMT(W38/1200,X38,-V38),2) -> 17439.41 | AC38: 0 | AD38: 0 | AE38: 101400 | AF38: 35900 | AG38: 13 | AH38: 25200 | AI38: 785 | AJ38: =ROUND(AB38/I38,4) -> 0.3419 | AK38: =IF(AND(AI38>=750,AJ38<=0.35),"Low",IF(AND(AI38>=600,AJ38<=0.5),"Medium","High")) -> Low | AL38: 1 | AM38: No | AN38: On Time | AO38: Approved | AP38: 0.137
A39: BPBL-CUS-000038 | B39: Nazrul Uddin | C39: Rashedul Patwary | D39: Male | E39: 40 | F39: Married | G39: Doctor | H39: PhD | I39: 159500 | J39: Self-Employed | K39: 15 | L39: Magura | M39: Khulna | N39: Rented House | O39: 1 | P39: BR-03 | Q39: BPBL Sonadanga Branch | R39: Khulna | S39: Khulna | T39: BPBL-LN-2026-000038 | U39: Agricultural Loan | V39: 225000 | W39: 8.01 | X39: 12 | Y39: 46194 | Z39: 46198 | AA39: 46202 | AB39: =ROUND(PMT(W39/1200,X39,-V39),2) -> 19573.44 | AC39: 0 | AD39: 0 | AE39: 221900 | AF39: 97800 | AG39: 19 | AI39: 900 | AJ39: =ROUND(AB39/I39,4) -> 0.1227 | AK39: =IF(AND(AI39>=750,AJ39<=0.35),"Low",IF(AND(AI39>=600,AJ39<=0.5),"Medium","High")) -> Low | AL39: 0 | AM39: No | AN39: On Time | AO39: Approved | AP39: 0.08
A40: BPBL-CUS-000039 | B40: Ruma Sikder | C40: Quamrul Pramanik | D40: Female | E40: 30 | F40: Married | G40: Retired | H40: Master's | I40: 71500 | J40: Retired | K40: 8 | L40: Tangail | M40: Dhaka | N40: Rented House | O40: 1 | P40: BR-14 | Q40: BPBL Victoria Road Branch | R40: Tangail | S40: Dhaka | T40: BPBL-LN-2026-000039 | U40: SME Loan | V40: 1192000 | W40: 10.64 | X40: 66 | Y40: 46190 | Z40: 46198 | AA40: 46199 | AB40: =ROUND(PMT(W40/1200,X40,-V40),2) -> 23935.36 | AC40: 1534000 | AD40: 3 | AE40: 234800 | AF40: 47200 | AG40: 29 | AH40: 30800 | AI40: 751 | AJ40: =ROUND(AB40/I40,4) -> 0.3348 | AK40: =IF(AND(AI40>=750,AJ40<=0.35),"Low",IF(AND(AI40>=600,AJ40<=0.5),"Medium","High")) -> Low | AL40: 0 | AM40: No | AN40: On Time | AO40: Approved | AP40: 0.172
A41: BPBL-CUS-000040 | B41: Tahmina Das | C41: Imran Saha | D41: Female | E41: 42 | F41: Single | G41: Retired | H41: Bachelor's | I41: 30000 | J41: Retired | K41: 23 | L41: Narayanganj | M41: Dhaka | N41: Rented House | O41: 0 | P41: BR-10 | Q41: BPBL Chashara Branch | R41: Narayanganj | S41: Dhaka | T41: BPBL-LN-2026-000040 | U41: SME Loan | V41: 393000 | W41: 12.35 | X41: 36 | Y41: 46179 | AB41: =ROUND(PMT(W41/1200,X41,-V41),2) -> 13119.02 | AC41: 540000 | AD41: 1 | AE41: 109500 | AF41: 32000 | AG41: 28 | AH41: 22000 | AI41: 699 | AJ41: =ROUND(AB41/I41,4) -> 0.4373 | AK41: =IF(AND(AI41>=750,AJ41<=0.35),"Low",IF(AND(AI41>=600,AJ41<=0.5),"Medium","High")) -> Medium | AL41: 2 | AM41: No | AO41: Pending | AP41: 0.19
A42: BPBL-CUS-000041 | B42: Emdadul Ahmed | C42: Nurul Hawlader | D42: Male | E42: 40 | F42: Married | G42: Self-Employed | I42: 62000 | J42: Self-Employed | K42: 15 | L42: Barishal | M42: Barishal | N42: Family Owned | O42: 0 | P42: BR-06 | Q42: BPBL Sadar Road Branch | R42: Barishal | S42: Barishal | T42: BPBL-LN-2026-000041 | U42: SME Loan | V42: 794000 | W42: 13.94 | X42: 66 | Y42: 46184 | Z42: 46186 | AA42: 46190 | AB42: =ROUND(PMT(W42/1200,X42,-V42),2) -> 17292.18 | AC42: 854000 | AD42: 2 | AE42: 192400 | AF42: 22500 | AG42: 16 | AH42: 46900 | AI42: 753 | AJ42: =ROUND(AB42/I42,4) -> 0.2789 | AK42: =IF(AND(AI42>=750,AJ42<=0.35),"Low",IF(AND(AI42>=600,AJ42<=0.5),"Medium","High")) -> Low | AL42: 1 | AM42: No | AN42: Delayed | AO42: Approved | AP42: 0.145
A43: BPBL-CUS-000042 | B43: Aminul Alam | C43: Mostafa Gazi | D43: Male | E43: 43 | F43: Single | G43: Engineer | H43: Bachelor's | I43: 115500 | J43: Private | K43: 20 | L43: Mymensingh | M43: Mymensingh | N43: Rented House | O43: 0 | P43: BR-08 | Q43: BPBL Notun Bazar Branch | R43: Mymensingh | S43: Mymensingh | T43: BPBL-LN-2026-000042 | U43: Agricultural Loan | V43: 662000 | W43: 7.8 | X43: 24 | Y43: 46196 | Z43: 46197 | AA43: 46203 | AB43: =ROUND(PMT(W43/1200,X43,-V43),2) -> 29880.12 | AC43: 0 | AD43: 1 | AE43: 338300 | AF43: 125600 | AG43: 46 | AH43: 57900 | AI43: 854 | AJ43: =ROUND(AB43/I43,4) -> 0.2587 | AK43: =IF(AND(AI43>=750,AJ43<=0.35),"Low",IF(AND(AI43>=600,AJ43<=0.5),"Medium","High")) -> Low | AL43: 0 | AM43: No | AN43: On Time | AO43: Approved | AP43: 0.117
A44: BPBL-CUS-000043 | B44: Beauty Roy | C44: Quamrul Karim | D44: Female | E44: 26 | F44: Widowed | G44: Private Service | H44: HSC | I44: 31000 | J44: Private | K44: 0 | L44: Dhaka | M44: Dhaka | N44: Rented House | O44: 1 | P44: BR-01 | Q44: BPBL Gulshan Branch | R44: Dhaka | S44: Dhaka | T44: BPBL-LN-2026-000043 | U44: Car Loan | V44: 338000 | W44: 11.7 | X44: 42 | Y44: 46189 | Z44: 46198 | AA44: 46200 | AB44: =ROUND(PMT(W44/1200,X44,-V44),2) -> 9846.14 | AC44: 441000 | AD44: 0 | AE44: 91100 | AF44: 51100 | AG44: 38 | AH44: 26800 | AI44: 756 | AJ44: =ROUND(AB44/I44,4) -> 0.3176 | AK44: =IF(AND(AI44>=750,AJ44<=0.35),"Low",IF(AND(AI44>=600,AJ44<=0.5),"Medium","High")) -> Low | AL44: 0 | AM44: No | AN44: On Time | AO44: Approved | AP44: 0.176
A45: BPBL-CUS-000044 | B45: Golam Hawlader | C45: Zahirul Mondol | D45: Male | E45: 40 | F45: Single | G45: Business Owner | H45: SSC | I45: 39500 | J45: Business | K45: 16 | L45: Narsingdi | M45: Dhaka | N45: Family Owned | O45: 0 | P45: BR-14 | Q45: BPBL Victoria Road Branch | R45: Tangail | S45: Dhaka | T45: BPBL-LN-2026-000044 | U45: SME Loan | V45: 645000 | W45: 14.37 | X45: 72 | Y45: 46201 | Z45: 46210 | AA45: 46214 | AB45: =ROUND(PMT(W45/1200,X45,-V45),2) -> 13418.83 | AC45: 685000 | AD45: 0 | AE45: 74900 | AF45: 9500 | AG45: 35 | AH45: 22400 | AI45: 728 | AJ45: =ROUND(AB45/I45,4) -> 0.3397 | AK45: =IF(AND(AI45>=750,AJ45<=0.35),"Low",IF(AND(AI45>=600,AJ45<=0.5),"Medium","High")) -> Medium | AL45: 2 | AM45: No | AN45: On Time | AO45: Approved | AP45: 0.328
A46: BPBL-CUS-000045 | B46: Poly Uddin | C46: Hasan Hossain | D46: Female | E46: 26 | F46: Married | G46: Teacher | H46: Bachelor's | I46: 21000 | J46: Private | K46: 0 | L46: Noakhali | M46: Chattogram | N46: Rented House | O46: 2 | P46: BR-15 | Q46: BPBL Maijdee Court Branch | R46: Noakhali | S46: Chattogram | T46: BPBL-LN-2026-000045 | U46: SME Loan | V46: 236000 | W46: 11.16 | X46: 24 | Y46: 46195 | AB46: =ROUND(PMT(W46/1200,X46,-V46),2) -> 11016.99 | AC46: 295000 | AD46: 0 | AE46: 37100 | AF46: 14500 | AG46: 25 | AH46: 16900 | AI46: 660 | AJ46: =ROUND(AB46/I46,4) -> 0.5246 | AK46: =IF(AND(AI46>=750,AJ46<=0.35),"Low",IF(AND(AI46>=600,AJ46<=0.5),"Medium","High")) -> High | AL46: 1 | AM46: No | AO46: Rejected | AP46: 0.306
A47: BPBL-CUS-000046 | B47: Rashida Khondkar | C47: Bashir Akter | D47: Female | E47: 35 | F47: Married | G47: Farmer | H47: HSC | I47: 13500 | J47: Self-Employed | K47: 12 | L47: Jessore | M47: Khulna | N47: Family Owned | O47: 0 | P47: BR-03 | Q47: BPBL Sonadanga Branch | R47: Khulna | S47: Khulna | T47: BPBL-LN-2026-000046 | U47: Agricultural Loan | V47: 50000 | W47: 8.09 | X47: 6 | Y47: 46199 | AB47: =ROUND(PMT(W47/1200,X47,-V47),2) -> 8531.07 | AC47: 0 | AD47: 2 | AE47: 9900 | AF47: 4800 | AG47: 12 | AH47: 8900 | AI47: 693 | AJ47: =ROUND(AB47/I47,4) -> 0.6319 | AK47: =IF(AND(AI47>=750,AJ47<=0.35),"Low",IF(AND(AI47>=600,AJ47<=0.5),"Medium","High")) -> High | AL47: 2 | AM47: Yes | AO47: Pending | AP47: 0.461
A48: BPBL-CUS-000047 | B48: Quamrul Akter | C48: Shamim Khan | D48: Male | E48: 21 | F48: Married | G48: Engineer | H48: Master's | I48: 136000 | J48: Private | K48: 0 | L48: Madaripur | M48: Dhaka | N48: Rented House | O48: 2 | P48: BR-14 | Q48: BPBL Victoria Road Branch | R48: Tangail | S48: Dhaka | T48: BPBL-LN-2026-000047 | U48: Car Loan | V48: 1556000 | W48: 10.4 | X48: 54 | Y48: 46183 | AB48: =ROUND(PMT(W48/1200,X48,-V48),2) -> 36203.94 | AC48: 2069000 | AD48: 0 | AE48: 77400 | AF48: 11800 | AG48: 12 | AH48: 127800 | AI48: 589 | AJ48: =ROUND(AB48/I48,4) -> 0.2662 | AK48: =IF(AND(AI48>=750,AJ48<=0.35),"Low",IF(AND(AI48>=600,AJ48<=0.5),"Medium","High")) -> High | AL48: 2 | AM48: No | AO48: Pending | AP48: 0.383
A49: BPBL-CUS-000048 | B49: Jasim Akand | C49: Jasim Sheikh | D49: Male | E49: 43 | F49: Married | G49: Government Service | H49: Bachelor's | I49: 39500 | J49: Government | K49: 23 | L49: Magura | M49: Khulna | N49: Own House | O49: 1 | P49: BR-13 | Q49: BPBL M.K. Road Branch | R49: Jessore | S49: Khulna | T49: BPBL-LN-2026-000048 | U49: Car Loan | V49: 308000 | W49: 11.94 | X49: 24 | Y49: 46187 | Z49: 46190 | AA49: 46192 | AB49: =ROUND(PMT(W49/1200,X49,-V49),2) -> 14490 | AC49: 353000 | AD49: 0 | AE49: 143200 | AF49: 72800 | AG49: 52 | AH49: 22700 | AI49: 794 | AJ49: =ROUND(AB49/I49,4) -> 0.3668 | AK49: =IF(AND(AI49>=750,AJ49<=0.35),"Low",IF(AND(AI49>=600,AJ49<=0.5),"Medium","High")) -> Medium | AL49: 1 | AM49: No | AN49: On Time | AO49: Approved | AP49: 0.085
A50: BPBL-CUS-000049 | B50: Mostafa Sikder | C50: Riaz Bhuiyan | D50: Male | E50: 30 | F50: Married | G50: Business Owner | H50: SSC | I50: 31000 | J50: Business | K50: 3 | L50: Bagerhat | M50: Khulna | N50: Rented House | O50: 1 | P50: BR-08 | Q50: BPBL Notun Bazar Branch | R50: Mymensingh | S50: Mymensingh | T50: BPBL-LN-2026-000049 | U50: Car Loan | V50: 574000 | W50: 13.51 | X50: 42 | Y50: 46185 | AB50: =ROUND(PMT(W50/1200,X50,-V50),2) -> 17226.89 | AC50: 831000 | AD50: 1 | AE50: 17900 | AF50: 4200 | AG50: 46 | AH50: 22700 | AI50: 485 | AJ50: =ROUND(AB50/I50,4) -> 0.5557 | AK50: =IF(AND(AI50>=750,AJ50<=0.35),"Low",IF(AND(AI50>=600,AJ50<=0.5),"Medium","High")) -> High | AL50: 3 | AM50: No | AO50: Pending | AP50: 0.45
A51: BPBL-CUS-000050 | B51: Robiul Islam | C51: Rashedul Das | D51: Male | E51: 23 | F51: Married | G51: Business Owner | H51: Bachelor's | I51: 86000 | J51: Business | K51: 0 | L51: Mymensingh | M51: Mymensingh | N51: Staff Quarters | O51: 0 | P51: BR-08 | Q51: BPBL Notun Bazar Branch | R51: Mymensingh | S51: Mymensingh | T51: BPBL-LN-2026-000050 | U51: Education Loan | V51: 367000 | W51: 10.39 | X51: 18 | Y51: 46195 | Z51: 46196 | AA51: 46201 | AB51: =ROUND(PMT(W51/1200,X51,-V51),2) -> 22106.91 | AC51: 0 | AD51: 2 | AE51: 209800 | AF51: 89300 | AG51: 35 | AH51: 82900 | AI51: 643 | AJ51: =ROUND(AB51/I51,4) -> 0.2571 | AK51: =IF(AND(AI51>=750,AJ51<=0.35),"Low",IF(AND(AI51>=600,AJ51<=0.5),"Medium","High")) -> Medium | AL51: 0 | AM51: No | AN51: Delayed | AO51: Approved | AP51: 0.21
A52: BPBL-CUS-000051 | B52: Jamal Akter | C52: Rashedul Mridha | D52: Male | E52: 40 | F52: Married | G52: Farmer | H52: HSC | I52: 27500 | J52: Self-Employed | K52: 17 | L52: Moulvibazar | M52: Sylhet | N52: Rented House | O52: 2 | P52: BR-14 | Q52: BPBL Victoria Road Branch | R52: Tangail | S52: Dhaka | T52: BPBL-LN-2026-000051 | U52: Agricultural Loan | V52: 60000 | W52: 7.84 | X52: 30 | Y52: 46183 | Z52: 46184 | AA52: 46189 | AB52: =ROUND(PMT(W52/1200,X52,-V52),2) -> 2208.9 | AC52: 0 | AD52: 1 | AE52: 37400 | AF52: 11000 | AG52: 17 | AH52: 14600 | AI52: 762 | AJ52: =ROUND(AB52/I52,4) -> 0.0803 | AK52: =IF(AND(AI52>=750,AJ52<=0.35),"Low",IF(AND(AI52>=600,AJ52<=0.5),"Medium","High")) -> Low | AL52: 0 | AM52: No | AN52: On Time | AO52: Closed | AP52: 0.174
A53: BPBL-CUS-000052 | B53: Mahmudul Uddin | C53: Shakil Mollah | D53: Male | E53: 52 | F53: Married | G53: Retired | H53: Bachelor's | I53: 28000 | J53: Retired | L53: Barishal | M53: Barishal | N53: Family Owned | O53: 1 | P53: BR-06 | Q53: BPBL Sadar Road Branch | R53: Barishal | S53: Barishal | T53: BPBL-LN-2026-000052 | U53: Agricultural Loan | V53: 110000 | W53: 7.4 | X53: 12 | Y53: 46183 | Z53: 46189 | AA53: 46190 | AB53: =ROUND(PMT(W53/1200,X53,-V53),2) -> 9538.24 | AC53: 0 | AD53: 0 | AE53: 62600 | AF53: 24900 | AG53: 29 | AH53: 15900 | AI53: 777 | AJ53: =ROUND(AB53/I53,4) -> 0.3407 | AK53: =IF(AND(AI53>=750,AJ53<=0.35),"Low",IF(AND(AI53>=600,AJ53<=0.5),"Medium","High")) -> Low | AL53: 1 | AM53: No | AN53: On Time | AO53: Closed | AP53: 0.144
A54: BPBL-CUS-000053 | B54: Razia Hasan | C54: Jasim Gazi | D54: Female | E54: 34 | F54: Single | G54: Freelancer | H54: HSC | I54: 34500 | J54: Self-Employed | K54: 12 | L54: Narsingdi | M54: Dhaka | N54: Rented House | O54: 0 | P54: BR-14 | Q54: BPBL Victoria Road Branch | R54: Tangail | S54: Dhaka | T54: BPBL-LN-2026-000053 | U54: SME Loan | V54: 474000 | W54: 13.4 | X54: 30 | Y54: 46192 | Z54: 46198 | AA54: 46199 | AB54: =ROUND(PMT(W54/1200,X54,-V54),2) -> 18681.23 | AC54: 614000 | AD54: 1 | AE54: 128000 | AF54: 21600 | AG54: 24 | AH54: 36600 | AI54: 650 | AJ54: =ROUND(AB54/I54,4) -> 0.5415 | AK54: =IF(AND(AI54>=750,AJ54<=0.35),"Low",IF(AND(AI54>=600,AJ54<=0.5),"Medium","High")) -> High | AL54: 2 | AM54: No | AN54: Delayed | AO54: Approved | AP54: 0.269
A55: BPBL-CUS-000054 | B55: Morsheda Hawlader | C55: Ekram Uddin | D55: Female | E55: 23 | F55: Married | G55: Engineer | H55: Bachelor's | I55: 78500 | J55: Private | K55: 3 | L55: Bogura | M55: Rajshahi | N55: Staff Quarters | O55: 4 | P55: BR-06 | Q55: BPBL Sadar Road Branch | R55: Barishal | S55: Barishal | T55: BPBL-LN-2026-000054 | U55: Car Loan | V55: 1310000 | W55: 12.71 | X55: 66 | Y55: 46177 | Z55: 46186 | AA55: 46188 | AB55: =ROUND(PMT(W55/1200,X55,-V55),2) -> 27688.58 | AC55: 1428000 | AD55: 2 | AE55: 48600 | AF55: 21800 | AG55: 29 | AH55: 42200 | AI55: 545 | AJ55: =ROUND(AB55/I55,4) -> 0.3527 | AK55: =IF(AND(AI55>=750,AJ55<=0.35),"Low",IF(AND(AI55>=600,AJ55<=0.5),"Medium","High")) -> High | AL55: 2 | AM55: No | AN55: On Time | AO55: Approved | AP55: 0.427
A56: BPBL-CUS-000055 | B56: Faruk Hawlader | C56: Zubayer Howlader | D56: Male | E56: 37 | F56: Married | G56: Retired | H56: SSC | I56: 24000 | J56: Retired | K56: 13 | L56: Noakhali | M56: Chattogram | O56: 3 | P56: BR-15 | Q56: BPBL Maijdee Court Branch | R56: Noakhali | S56: Chattogram | T56: BPBL-LN-2026-000055 | U56: Agricultural Loan | V56: 216000 | W56: 8.02 | X56: 24 | Y56: 46177 | AB56: =ROUND(PMT(W56/1200,X56,-V56),2) -> 9771.07 | AC56: 0 | AD56: 0 | AE56: 17500 | AF56: 4500 | AG56: 15 | AH56: 17600 | AI56: 584 | AJ56: =ROUND(AB56/I56,4) -> 0.4071 | AK56: =IF(AND(AI56>=750,AJ56<=0.35),"Low",IF(AND(AI56>=600,AJ56<=0.5),"Medium","High")) -> High | AL56: 0 | AM56: No | AO56: Pending | AP56: 0.38
A57: BPBL-CUS-000056 | B57: Rezaul Mollah | C57: Ashraf Uddin | D57: Male | E57: 30 | F57: Single | G57: Farmer | H57: HSC | I57: 25000 | J57: Self-Employed | K57: 9 | L57: Dhaka | M57: Dhaka | N57: Own House | O57: 0 | P57: BR-01 | Q57: BPBL Gulshan Branch | R57: Dhaka | S57: Dhaka | T57: BPBL-LN-2026-000056 | U57: SME Loan | V57: 273000 | W57: 13.39 | X57: 42 | Y57: 46199 | Z57: 46201 | AA57: 46206 | AB57: =ROUND(PMT(W57/1200,X57,-V57),2) -> 8177.19 | AC57: 339000 | AD57: 2 | AE57: 98600 | AF57: 47700 | AG57: 32 | AH57: 15900 | AI57: 772 | AJ57: =ROUND(AB57/I57,4) -> 0.3271 | AK57: =IF(AND(AI57>=750,AJ57<=0.35),"Low",IF(AND(AI57>=600,AJ57<=0.5),"Medium","High")) -> Low | AL57: 2 | AM57: No | AN57: On Time | AO57: Approved | AP57: 0.223
A58: BPBL-CUS-000057 | B58: Mukta Pramanik | C58: Tanvir Sarkar | D58: Female | E58: 55 | F58: Married | G58: Housewife | H58: HSC | I58: 16500 | J58: Unemployed | K58: 35 | L58: Manikganj | M58: Dhaka | N58: Rented House | O58: 1 | P58: BR-13 | Q58: BPBL M.K. Road Branch | R58: Jessore | S58: Khulna | T58: BPBL-LN-2026-000057 | U58: Personal Loan | V58: 171000 | W58: 11.76 | X58: 60 | Y58: 46199 | AB58: =ROUND(PMT(W58/1200,X58,-V58),2) -> 3783.09 | AC58: 0 | AD58: 0 | AE58: 47500 | AF58: 9900 | AG58: 11 | AH58: 17500 | AI58: 630 | AJ58: =ROUND(AB58/I58,4) -> 0.2293 | AK58: =IF(AND(AI58>=750,AJ58<=0.35),"Low",IF(AND(AI58>=600,AJ58<=0.5),"Medium","High")) -> Medium | AL58: 1 | AM58: Yes | AO58: Rejected | AP58: 0.324
A59: BPBL-CUS-000058 | B59: Farzana Islam | C59: Liton Khondkar | D59: Female | E59: 48 | F59: Married | G59: Doctor | H59: Bachelor's | I59: 136500 | J59: Self-Employed | K59: 22 | L59: Sylhet | M59: Sylhet | N59: Staff Quarters | O59: 3 | P59: BR-05 | Q59: BPBL Zindabazar Branch | R59: Sylhet | S59: Sylhet | T59: BPBL-LN-2026-000058 | U59: Personal Loan | V59: 848000 | W59: 12.55 | X59: 18 | Y59: 46201 | Z59: 46206 | AA59: 46210 | AB59: =ROUND(PMT(W59/1200,X59,-V59),2) -> 51929.69 | AC59: 0 | AD59: 1 | AE59: 440700 | AF59: 121200 | AG59: 20 | AH59: 47300 | AI59: 742 | AJ59: =ROUND(AB59/I59,4) -> 0.3804 | AK59: =IF(AND(AI59>=750,AJ59<=0.35),"Low",IF(AND(AI59>=600,AJ59<=0.5),"Medium","High")) -> Medium | AL59: 1 | AM59: No | AN59: On Time | AO59: Closed | AP59: 0.174
A60: BPBL-CUS-000059 | B60: Jahangir Mridha | C60: Ataur Roy | D60: Male | E60: 33 | F60: Married | G60: Farmer | H60: Below SSC | I60: 9000 | J60: Self-Employed | K60: 11 | L60: Gaibandha | M60: Rangpur | N60: Rented House | O60: 2 | P60: BR-07 | Q60: BPBL Jahaj Company Mor Branch | R60: Rangpur | S60: Rangpur | T60: BPBL-LN-2026-000059 | U60: Agricultural Loan | V60: 50000 | W60: 10.1 | X60: 12 | Y60: 46186 | AB60: =ROUND(PMT(W60/1200,X60,-V60),2) -> 4398.12 | AC60: 0 | AD60: 1 | AE60: 21900 | AF60: 3100 | AG60: 43 | AI60: 711 | AJ60: =ROUND(AB60/I60,4) -> 0.4887 | AK60: =IF(AND(AI60>=750,AJ60<=0.35),"Low",IF(AND(AI60>=600,AJ60<=0.5),"Medium","High")) -> Medium | AL60: 2 | AM60: No | AO60: Pending | AP60: 0.264
A61: BPBL-CUS-000060 | B61: Liza Bhuiyan | C61: Faruk Uddin | D61: Female | E61: 22 | G61: Teacher | H61: Bachelor's | I61: 27500 | J61: Private | K61: 0 | L61: Gazipur | M61: Dhaka | N61: Family Owned | O61: 1 | P61: BR-10 | Q61: BPBL Chashara Branch | R61: Narayanganj | S61: Dhaka | T61: BPBL-LN-2026-000060 | U61: Education Loan | V61: 224000 | W61: 9.9 | X61: 48 | Y61: 46186 | Z61: 46188 | AA61: 46191 | AB61: =ROUND(PMT(W61/1200,X61,-V61),2) -> 5670.47 | AC61: 0 | AD61: 0 | AE61: 93100 | AF61: 25500 | AG61: 20 | AH61: 23200 | AI61: 763 | AJ61: =ROUND(AB61/I61,4) -> 0.2062 | AK61: =IF(AND(AI61>=750,AJ61<=0.35),"Low",IF(AND(AI61>=600,AJ61<=0.5),"Medium","High")) -> Low | AL61: 0 | AM61: No | AN61: On Time | AO61: Approved | AP61: 0.267
A62: BPBL-CUS-000061 | B62: Delwar Sardar | C62: Sohel Khan | D62: Male | E62: 21 | F62: Married | G62: Teacher | H62: Master's | I62: 49000 | J62: Private | K62: 1 | L62: Cumilla | M62: Chattogram | N62: Rented House | O62: 6 | P62: BR-11 | Q62: BPBL Kandirpar Branch | R62: Cumilla | S62: Chattogram | T62: BPBL-LN-2026-000061 | U62: Education Loan | V62: 1014000 | W62: 9.79 | X62: 72 | Y62: 46177 | Z62: 46184 | AA62: 46190 | AB62: =ROUND(PMT(W62/1200,X62,-V62),2) -> 18678 | AC62: 0 | AD62: 1 | AE62: 152000 | AF62: 27400 | AG62: 16 | AH62: 46800 | AI62: 840 | AJ62: =ROUND(AB62/I62,4) -> 0.3812 | AK62: =IF(AND(AI62>=750,AJ62<=0.35),"Low",IF(AND(AI62>=600,AJ62<=0.5),"Medium","High")) -> Medium | AL62: 0 | AM62: No | AN62: On Time | AO62: Approved | AP62: 0.08
A63: BPBL-CUS-000062 | B63: Jasim Gazi | C63: Tanvir Patwary | D63: Male | E63: 38 | F63: Single | G63: Self-Employed | H63: HSC | I63: 58000 | J63: Self-Employed | K63: 17 | L63: Narayanganj | M63: Dhaka | N63: Rented House | O63: 0 | P63: BR-10 | Q63: BPBL Chashara Branch | R63: Narayanganj | S63: Dhaka | T63: BPBL-LN-2026-000062 | U63: Business Loan | V63: 692000 | W63: 14.54 | X63: 48 | Y63: 46198 | AB63: =ROUND(PMT(W63/1200,X63,-V63),2) -> 19097.9 | AC63: 962000 | AE63: 138900 | AF63: 80800 | AG63: 22 | AH63: 33300 | AI63: 754 | AJ63: =ROUND(AB63/I63,4) -> 0.3293 | AK63: =IF(AND(AI63>=750,AJ63<=0.35),"Low",IF(AND(AI63>=600,AJ63<=0.5),"Medium","High")) -> Low | AL63: 1 | AM63: No | AO63: Rejected | AP63: 0.199
A64: BPBL-CUS-000063 | B64: Salma Munshi | C64: Mostafa Pramanik | D64: Female | E64: 44 | F64: Married | G64: Housewife | H64: SSC | I64: 15500 | J64: Unemployed | K64: 20 | L64: Manikganj | M64: Dhaka | N64: Own House | O64: 0 | P64: BR-01 | Q64: BPBL Gulshan Branch | R64: Dhaka | S64: Dhaka | T64: BPBL-LN-2026-000063 | U64: Business Loan | V64: 300000 | W64: 14.14 | X64: 36 | Y64: 46197 | Z64: 46204 | AA64: 46208 | AB64: =ROUND(PMT(W64/1200,X64,-V64),2) -> 10273.7 | AC64: 393000 | AD64: 2 | AE64: 48900 | AF64: 5500 | AG64: 33 | AH64: 4900 | AI64: 810 | AJ64: =ROUND(AB64/I64,4) -> 0.6628 | AK64: =IF(AND(AI64>=750,AJ64<=0.35),"Low",IF(AND(AI64>=600,AJ64<=0.5),"Medium","High")) -> High | AL64: 0 | AM64: Yes | AN64: Delayed | AO64: Closed | AP64: 0.2
A65: BPBL-CUS-000064 | B65: Kamal Mridha | C65: Towhid Das | D65: Male | E65: 36 | F65: Single | G65: Government Service | H65: HSC | I65: 20000 | J65: Government | K65: 11 | L65: Chattogram | M65: Chattogram | N65: Rented House | O65: 1 | P65: BR-13 | Q65: BPBL M.K. Road Branch | R65: Jessore | S65: Khulna | T65: BPBL-LN-2026-000064 | U65: Car Loan | V65: 300000 | W65: 10.72 | X65: 18 | Y65: 46182 | Z65: 46191 | AA65: 46192 | AB65: =ROUND(PMT(W65/1200,X65,-V65),2) -> 18116.74 | AC65: 402000 | AD65: 0 | AF65: 13400 | AG65: 40 | AH65: 12900 | AI65: 564 | AJ65: =ROUND(AB65/I65,4) -> 0.9058 | AK65: =IF(AND(AI65>=750,AJ65<=0.35),"Low",IF(AND(AI65>=600,AJ65<=0.5),"Medium","High")) -> High | AL65: 2 | AM65: No | AN65: On Time | AO65: Approved | AP65: 0.325
A66: BPBL-CUS-000065 | B66: Shahidul Karim | C66: Zahirul Hawlader | D66: Male | E66: 36 | F66: Married | G66: Government Service | H66: Bachelor's | I66: 59000 | J66: Government | K66: 14 | L66: Gazipur | M66: Dhaka | N66: Family Owned | O66: 2 | P66: BR-09 | Q66: BPBL Chandona Chowrasta Branch | R66: Gazipur | S66: Dhaka | T66: BPBL-LN-2026-000065 | U66: Home Loan | V66: 1832000 | W66: 10.45 | X66: 150 | Y66: 46189 | AB66: =ROUND(PMT(W66/1200,X66,-V66),2) -> 21925.51 | AC66: 2624000 | AD66: 1 | AE66: 67800 | AF66: 36200 | AG66: 27 | AH66: 54400 | AI66: 703 | AJ66: =ROUND(AB66/I66,4) -> 0.3716 | AK66: =IF(AND(AI66>=750,AJ66<=0.35),"Low",IF(AND(AI66>=600,AJ66<=0.5),"Medium","High")) -> Medium | AL66: 1 | AM66: Yes | AO66: Rejected | AP66: 0.355
A67: BPBL-CUS-000066 | B67: Abdul Alam | C67: Forhad Mondol | D67: Male | E67: 44 | F67: Single | G67: Government Service | H67: HSC | I67: 46500 | J67: Government | K67: 19 | L67: Naogaon | M67: Rajshahi | N67: Family Owned | O67: 1 | P67: BR-12 | Q67: BPBL Satmatha Branch | R67: Bogura | S67: Rajshahi | T67: BPBL-LN-2026-000066 | U67: SME Loan | V67: 363000 | W67: 10.6 | X67: 24 | Y67: 46196 | Z67: 46201 | AA67: 46202 | AB67: =ROUND(PMT(W67/1200,X67,-V67),2) -> 16851.31 | AC67: 487000 | AD67: 0 | AE67: 103300 | AF67: 13600 | AG67: 23 | AH67: 35600 | AI67: 849 | AJ67: =ROUND(AB67/I67,4) -> 0.3624 | AK67: =IF(AND(AI67>=750,AJ67<=0.35),"Low",IF(AND(AI67>=600,AJ67<=0.5),"Medium","High")) -> Medium | AL67: 0 | AM67: No | AN67: On Time | AO67: Closed | AP67: 0.032
A68: BPBL-CUS-000067 | B68: Mahmudul Roy | C68: Selim Chowdhury | D68: Male | E68: 47 | F68: Married | G68: Farmer | H68: SSC | I68: 14500 | J68: Self-Employed | K68: 21 | L68: Tangail | M68: Dhaka | N68: Own House | O68: 1 | P68: BR-14 | Q68: BPBL Victoria Road Branch | R68: Tangail | S68: Dhaka | T68: BPBL-LN-2026-000067 | U68: SME Loan | V68: 200000 | W68: 13.27 | X68: 72 | Y68: 46184 | AB68: =ROUND(PMT(W68/1200,X68,-V68),2) -> 4043.38 | AC68: 278000 | AD68: 0 | AE68: 12600 | AF68: 2800 | AG68: 20 | AH68: 15800 | AI68: 702 | AJ68: =ROUND(AB68/I68,4) -> 0.2789 | AK68: =IF(AND(AI68>=750,AJ68<=0.35),"Low",IF(AND(AI68>=600,AJ68<=0.5),"Medium","High")) -> Medium | AL68: 2 | AM68: No | AO68: Rejected | AP68: 0.249
A69: BPBL-CUS-000068 | B69: Mahmudul Sarkar | C69: Robiul Das | D69: Male | E69: 37 | F69: Widowed | G69: Engineer | H69: Bachelor's | I69: 70500 | J69: Private | K69: 16 | L69: Munshiganj | M69: Dhaka | N69: Own House | O69: 0 | P69: BR-09 | Q69: BPBL Chandona Chowrasta Branch | R69: Gazipur | S69: Dhaka | T69: BPBL-LN-2026-000068 | U69: Home Loan | V69: 2271000 | W69: 8.92 | X69: 156 | Y69: 46198 | AB69: =ROUND(PMT(W69/1200,X69,-V69),2) -> 24642.48 | AC69: 2422000 | AD69: 1 | AE69: 232800 | AF69: 46600 | AG69: 36 | AH69: 30600 | AI69: 628 | AJ69: =ROUND(AB69/I69,4) -> 0.3495 | AK69: =IF(AND(AI69>=750,AJ69<=0.35),"Low",IF(AND(AI69>=600,AJ69<=0.5),"Medium","High")) -> Medium | AL69: 1 | AM69: No | AO69: Rejected | AP69: 0.376
A70: BPBL-CUS-000069 | B70: Jesmin Mondol | C70: Nayeem Hossain | D70: Female | E70: 41 | F70: Single | G70: Retired | H70: Bachelor's | I70: 25000 | J70: Retired | L70: Sherpur | M70: Mymensingh | N70: Rented House | O70: 1 | P70: BR-08 | Q70: BPBL Notun Bazar Branch | R70: Mymensingh | S70: Mymensingh | T70: BPBL-LN-2026-000069 | U70: SME Loan | V70: 253000 | W70: 13.24 | X70: 36 | Y70: 46199 | Z70: 46200 | AA70: 46203 | AB70: =ROUND(PMT(W70/1200,X70,-V70),2) -> 8553.85 | AC70: 356000 | AD70: 1 | AE70: 52100 | AF70: 22000 | AG70: 30 | AH70: 18000 | AI70: 887 | AJ70: =ROUND(AB70/I70,4) -> 0.3422 | AK70: =IF(AND(AI70>=750,AJ70<=0.35),"Low",IF(AND(AI70>=600,AJ70<=0.5),"Medium","High")) -> Low | AL70: 1 | AM70: No | AN70: On Time | AO70: Approved | AP70: 0.119
A71: BPBL-CUS-000070 | B71: Ferdousi Uddin | C71: Rakib Majumder | D71: Female | E71: 33 | F71: Divorced | G71: Housewife | H71: Bachelor's | I71: 20500 | J71: Unemployed | K71: 8 | L71: Dhaka | M71: Dhaka | N71: Rented House | O71: 0 | P71: BR-01 | Q71: BPBL Gulshan Branch | R71: Dhaka | S71: Dhaka | T71: BPBL-LN-2026-000070 | U71: Business Loan | V71: 300000 | W71: 15.3 | X71: 30 | Y71: 46184 | AB71: =ROUND(PMT(W71/1200,X71,-V71),2) -> 12096.98 | AC71: 449000 | AD71: 0 | AE71: 24600 | AF71: 10800 | AG71: 29 | AH71: 7300 | AI71: 620 | AJ71: =ROUND(AB71/I71,4) -> 0.5901 | AK71: =IF(AND(AI71>=750,AJ71<=0.35),"Low",IF(AND(AI71>=600,AJ71<=0.5),"Medium","High")) -> High | AL71: 3 | AM71: No | AO71: Rejected | AP71: 0.341
A72: BPBL-CUS-000071 | B72: Bashir Biswas | C72: Mahmudul Biswas | D72: Male | E72: 50 | F72: Married | G72: Business Owner | H72: HSC | I72: 71000 | J72: Business | K72: 24 | L72: Cumilla | M72: Chattogram | N72: Own House | O72: 3 | P72: BR-02 | Q72: BPBL Agrabad Branch | R72: Chattogram | S72: Chattogram | T72: BPBL-LN-2026-000071 | U72: Business Loan | V72: 1525000 | W72: 13.81 | X72: 72 | Y72: 46198 | Z72: 46208 | AA72: 46209 | AB72: =ROUND(PMT(W72/1200,X72,-V72),2) -> 31268.81 | AC72: 2212000 | AD72: 0 | AE72: 182700 | AF72: 101600 | AG72: 19 | AH72: 33300 | AI72: 749 | AJ72: =ROUND(AB72/I72,4) -> 0.4404 | AK72: =IF(AND(AI72>=750,AJ72<=0.35),"Low",IF(AND(AI72>=600,AJ72<=0.5),"Medium","High")) -> Medium | AL72: 1 | AM72: No | AN72: Delayed | AO72: Approved | AP72: 0.127
A73: BPBL-CUS-000072 | B73: Imran Sardar | C73: Golam Akand | D73: Male | E73: 54 | F73: Single | G73: Retired | I73: 43500 | J73: Retired | K73: 31 | L73: Chattogram | M73: Chattogram | N73: Rented House | O73: 1 | P73: BR-02 | Q73: BPBL Agrabad Branch | R73: Chattogram | S73: Chattogram | T73: BPBL-LN-2026-000072 | U73: Personal Loan | V73: 361000 | W73: 15.7 | X73: 36 | Y73: 46194 | Z73: 46201 | AA73: 46203 | AB73: =ROUND(PMT(W73/1200,X73,-V73),2) -> 12638.29 | AC73: 0 | AD73: 2 | AE73: 112000 | AF73: 20400 | AG73: 31 | AH73: 26700 | AI73: 763 | AJ73: =ROUND(AB73/I73,4) -> 0.2905 | AK73: =IF(AND(AI73>=750,AJ73<=0.35),"Low",IF(AND(AI73>=600,AJ73<=0.5),"Medium","High")) -> Low | AL73: 1 | AM73: No | AN73: On Time | AO73: Approved | AP73: 0.09
A74: BPBL-CUS-000073 | B74: Tariqul Khan | C74: Hossain Hawlader | D74: Male | E74: 23 | F74: Single | G74: Farmer | H74: Below SSC | I74: 15500 | J74: Self-Employed | K74: 0 | L74: Khagrachari | M74: Chattogram | N74: Own House | O74: 1 | P74: BR-11 | Q74: BPBL Kandirpar Branch | R74: Cumilla | S74: Chattogram | T74: BPBL-LN-2026-000073 | U74: SME Loan | V74: 200000 | W74: 11.51 | X74: 54 | Y74: 46189 | Z74: 46192 | AA74: 46194 | AB74: =ROUND(PMT(W74/1200,X74,-V74),2) -> 4762.65 | AC74: 271000 | AD74: 1 | AF74: 4500 | AH74: 12900 | AI74: 695 | AJ74: =ROUND(AB74/I74,4) -> 0.3073 | AK74: =IF(AND(AI74>=750,AJ74<=0.35),"Low",IF(AND(AI74>=600,AJ74<=0.5),"Medium","High")) -> Medium | AL74: 2 | AM74: No | AN74: On Time | AO74: Approved | AP74: 0.243
A75: BPBL-CUS-000074 | B75: Jesmin Saha | C75: Zubayer Mia | D75: Female | E75: 51 | F75: Married | G75: Private Service | H75: HSC | I75: 50000 | J75: Private | K75: 28 | L75: Munshiganj | M75: Dhaka | N75: Own House | O75: 3 | P75: BR-14 | Q75: BPBL Victoria Road Branch | R75: Tangail | S75: Dhaka | T75: BPBL-LN-2026-000074 | U75: Car Loan | V75: 505000 | W75: 9.93 | X75: 36 | Y75: 46188 | Z75: 46196 | AA75: 46198 | AB75: =ROUND(PMT(W75/1200,X75,-V75),2) -> 16278.34 | AC75: 741000 | AD75: 0 | AE75: 32300 | AF75: 5600 | AG75: 2 | AH75: 54500 | AI75: 723 | AJ75: =ROUND(AB75/I75,4) -> 0.3256 | AK75: =IF(AND(AI75>=750,AJ75<=0.35),"Low",IF(AND(AI75>=600,AJ75<=0.5),"Medium","High")) -> Medium | AL75: 2 | AM75: No | AN75: On Time | AO75: Approved | AP75: 0.234
A76: BPBL-CUS-000075 | B76: Masud Sarker | C76: Tariqul Chowdhury | D76: Male | E76: 39 | F76: Married | G76: Self-Employed | H76: Bachelor's | I76: 58500 | J76: Self-Employed | K76: 18 | L76: Pirojpur | M76: Barishal | N76: Family Owned | O76: 3 | P76: BR-06 | Q76: BPBL Sadar Road Branch | R76: Barishal | S76: Barishal | T76: BPBL-LN-2026-000075 | U76: Home Loan | V76: 2108000 | W76: 10.67 | X76: 168 | Y76: 46194 | Z76: 46200 | AA76: 46205 | AB76: =ROUND(PMT(W76/1200,X76,-V76),2) -> 24216.74 | AD76: 1 | AE76: 200900 | AF76: 115000 | AH76: 49500 | AI76: 641 | AJ76: =ROUND(AB76/I76,4) -> 0.414 | AK76: =IF(AND(AI76>=750,AJ76<=0.35),"Low",IF(AND(AI76>=600,AJ76<=0.5),"Medium","High")) -> Medium | AL76: 2 | AM76: No | AN76: Missed Payment | AO76: Approved | AP76: 0.328
A77: BPBL-CUS-000076 | B77: Faruk Mollah | C77: Tanvir Pramanik | D77: Male | E77: 64 | F77: Married | G77: Freelancer | H77: HSC | I77: 38500 | J77: Self-Employed | K77: 40 | L77: Sylhet | M77: Sylhet | N77: Family Owned | O77: 2 | P77: BR-05 | Q77: BPBL Zindabazar Branch | R77: Sylhet | S77: Sylhet | T77: BPBL-LN-2026-000076 | U77: Agricultural Loan | V77: 4982092 | W77: 9.27 | X77: 12 | Y77: 46186 | Z77: 46190 | AA77: 46194 | AB77: =ROUND(PMT(W77/1200,X77,-V77),2) -> 436315.34 | AC77: 0 | AD77: 2 | AE77: 124700 | AF77: 47800 | AG77: 24 | AH77: 34300 | AI77: 775 | AJ77: =ROUND(AB77/I77,4) -> 11.3329 | AK77: =IF(AND(AI77>=750,AJ77<=0.35),"Low",IF(AND(AI77>=600,AJ77<=0.5),"Medium","High")) -> High | AL77: 0 | AM77: No | AN77: Missed Payment | AO77: Approved | AP77: 0.195
A78: BPBL-CUS-000077 | B78: Nipa Sarker | C78: Shamim Chowdhury | D78: Female | E78: 35 | F78: Married | G78: Freelancer | H78: Master's | I78: 66000 | J78: Self-Employed | K78: 12 | L78: Brahmanbaria | M78: Chattogram | N78: Rented House | O78: 2 | P78: BR-15 | Q78: BPBL Maijdee Court Branch | R78: Noakhali | S78: Chattogram | T78: BPBL-LN-2026-000077 | U78: Personal Loan | V78: 580000 | W78: 13.09 | X78: 30 | Y78: 46182 | Z78: 46185 | AA78: 46190 | AB78: =ROUND(PMT(W78/1200,X78,-V78),2) -> 22773.31 | AC78: 0 | AD78: 2 | AE78: 122800 | AG78: 16 | AH78: 32300 | AI78: 714 | AJ78: =ROUND(AB78/I78,4) -> 0.3451 | AK78: =IF(AND(AI78>=750,AJ78<=0.35),"Low",IF(AND(AI78>=600,AJ78<=0.5),"Medium","High")) -> Medium | AL78: 1 | AM78: Yes | AN78: Missed Payment | AO78: Approved | AP78: 0.389
A79: BPBL-CUS-000078 | B79: Shamim Ahmed | C79: Jasim Howlader | D79: Male | E79: 23 | F79: Married | G79: Freelancer | H79: Bachelor's | I79: 30500 | J79: Self-Employed | K79: 4 | L79: Jessore | M79: Khulna | N79: Family Owned | O79: 0 | P79: BR-13 | Q79: BPBL M.K. Road Branch | R79: Jessore | S79: Khulna | T79: BPBL-LN-2026-000078 | U79: Education Loan | V79: 207000 | W79: 9.11 | X79: 12 | Y79: 46194 | Z79: 46198 | AA79: 46204 | AB79: =ROUND(PMT(W79/1200,X79,-V79),2) -> 18113.02 | AC79: 0 | AD79: 1 | AE79: 57800 | AF79: 22500 | AG79: 6 | AH79: 22200 | AI79: 631 | AJ79: =ROUND(AB79/I79,4) -> 0.5939 | AK79: =IF(AND(AI79>=750,AJ79<=0.35),"Low",IF(AND(AI79>=600,AJ79<=0.5),"Medium","High")) -> High | AL79: 2 | AM79: No | AN79: On Time | AO79: Closed | AP79: 0.269
A80: BPBL-CUS-000079 | B80: Liza Khan | C80: Robiul Biswas | D80: Female | E80: 53 | F80: Married | G80: Retired | H80: SSC | I80: 27000 | J80: Retired | K80: 26 | L80: Rajshahi | M80: Rajshahi | N80: Own House | O80: 3 | P80: BR-04 | Q80: BPBL Shaheb Bazar Branch | R80: Rajshahi | S80: Rajshahi | T80: BPBL-LN-2026-000079 | U80: Car Loan | V80: 300000 | W80: 13.23 | X80: 36 | Y80: 46197 | Z80: 46199 | AA80: 46202 | AB80: =ROUND(PMT(W80/1200,X80,-V80),2) -> 10141.45 | AC80: 315000 | AD80: 0 | AE80: 40400 | AF80: 10200 | AG80: 26 | AH80: 25400 | AI80: 705 | AJ80: =ROUND(AB80/I80,4) -> 0.3756 | AK80: =IF(AND(AI80>=750,AJ80<=0.35),"Low",IF(AND(AI80>=600,AJ80<=0.5),"Medium","High")) -> Medium | AL80: 1 | AM80: No | AN80: On Time | AO80: Approved | AP80: 0.165
A81: BPBL-CUS-000080 | B81: Jesmin Roy | C81: Monir Hawlader | D81: Female | E81: 21 | F81: Single | G81: Farmer | H81: Below SSC | I81: 12500 | J81: Self-Employed | K81: 1 | L81: Satkhira | M81: Khulna | N81: Rented House | O81: 0 | P81: BR-03 | Q81: BPBL Sonadanga Branch | R81: Khulna | S81: Khulna | T81: BPBL-LN-2026-000080 | U81: Agricultural Loan | V81: 89000 | W81: 9.35 | X81: 24 | Y81: 46180 | Z81: 46184 | AA81: 46185 | AB81: =ROUND(PMT(W81/1200,X81,-V81),2) -> 4080.25 | AC81: 0 | AD81: 1 | AE81: 17500 | AF81: 10200 | AG81: 14 | AH81: 8600 | AI81: 592 | AJ81: =ROUND(AB81/I81,4) -> 0.3264 | AK81: =IF(AND(AI81>=750,AJ81<=0.35),"Low",IF(AND(AI81>=600,AJ81<=0.5),"Medium","High")) -> High | AL81: 2 | AM81: Yes | AN81: On Time | AO81: Approved | AP81: 0.457
A82: BPBL-CUS-000081 | B82: Hasan Das | C82: Faruk Sarker | D82: Male | E82: 40 | F82: Single | G82: Government Service | H82: Master's | I82: 90500 | J82: Government | K82: 15 | L82: Jamalpur | M82: Mymensingh | N82: Own House | O82: 0 | P82: BR-08 | Q82: BPBL Notun Bazar Branch | R82: Mymensingh | S82: Mymensingh | T82: BPBL-LN-2026-000081 | U82: Car Loan | V82: 1173000 | W82: 10.23 | X82: 48 | Y82: 46197 | Z82: 46204 | AA82: 46207 | AB82: =ROUND(PMT(W82/1200,X82,-V82),2) -> 29880.04 | AC82: 1414000 | AD82: 2 | AE82: 292500 | AF82: 69400 | AG82: 18 | AH82: 86700 | AI82: 746 | AJ82: =ROUND(AB82/I82,4) -> 0.3302 | AK82: =IF(AND(AI82>=750,AJ82<=0.35),"Low",IF(AND(AI82>=600,AJ82<=0.5),"Medium","High")) -> Medium | AL82: 0 | AM82: No | AN82: Missed Payment | AO82: Approved | AP82: 0.131
A83: BPBL-CUS-000082 | B83: Mizanur Majumder | C83: Sohel Majumder | D83: Male | E83: 58 | F83: Divorced | H83: Bachelor's | I83: 52000 | J83: Private | K83: 35 | L83: Sylhet | M83: Sylhet | O83: 0 | P83: BR-05 | Q83: BPBL Zindabazar Branch | R83: Sylhet | S83: Sylhet | T83: BPBL-LN-2026-000082 | U83: SME Loan | V83: 225000 | W83: 11.11 | X83: 12 | Y83: 46193 | AB83: =ROUND(PMT(W83/1200,X83,-V83),2) -> 19897.42 | AC83: 297000 | AD83: 1 | AE83: 68200 | AF83: 20100 | AG83: 58 | AH83: 40300 | AI83: 610 | AJ83: =ROUND(AB83/I83,4) -> 0.3826 | AK83: =IF(AND(AI83>=750,AJ83<=0.35),"Low",IF(AND(AI83>=600,AJ83<=0.5),"Medium","High")) -> Medium | AL83: 2 | AM83: No | AO83: Rejected | AP83: 0.373
A84: BPBL-CUS-000083 | B84: Sadia Karim | C84: Mahmudul Sheikh | D84: Female | E84: 41 | F84: Married | G84: Retired | H84: SSC | I84: 20000 | J84: Retired | K84: 15 | L84: Kishoreganj | M84: Dhaka | N84: Rented House | O84: 0 | P84: BR-01 | Q84: BPBL Gulshan Branch | R84: Dhaka | S84: Dhaka | T84: BPBL-LN-2026-000083 | U84: Agricultural Loan | V84: 109000 | W84: 7.39 | X84: 24 | Y84: 46174 | Z84: 46184 | AA84: 46190 | AB84: =ROUND(PMT(W84/1200,X84,-V84),2) -> 4899.51 | AC84: 0 | AD84: 1 | AE84: 15600 | AF84: 2200 | AG84: 35 | AH84: 20300 | AI84: 867 | AJ84: =ROUND(AB84/I84,4) -> 0.245 | AK84: =IF(AND(AI84>=750,AJ84<=0.35),"Low",IF(AND(AI84>=600,AJ84<=0.5),"Medium","High")) -> Low | AL84: 2 | AM84: No | AN84: On Time | AO84: Approved | AP84: 0.034
A85: BPBL-CUS-000084 | B85: Farzana Sarkar | C85: Hasan Sarker | D85: Female | E85: 31 | F85: Married | G85: Housewife | H85: Bachelor's | I85: 14000 | J85: Unemployed | K85: 6 | L85: Jessore | M85: Khulna | N85: Rented House | O85: 1 | P85: BR-13 | Q85: BPBL M.K. Road Branch | R85: Jessore | S85: Khulna | T85: BPBL-LN-2026-000084 | U85: Personal Loan | V85: 102000 | W85: 13.29 | X85: 24 | Y85: 46185 | Z85: 46190 | AA85: 46192 | AB85: =ROUND(PMT(W85/1200,X85,-V85),2) -> 4863.17 | AC85: 0 | AD85: 0 | AE85: 42800 | AF85: 14200 | AH85: 4900 | AI85: 633 | AJ85: =ROUND(AB85/I85,4) -> 0.3474 | AK85: =IF(AND(AI85>=750,AJ85<=0.35),"Low",IF(AND(AI85>=600,AJ85<=0.5),"Medium","High")) -> Medium | AL85: 5 | AM85: Yes | AN85: Missed Payment | AO85: Approved | AP85: 0.484
A86: BPBL-CUS-000085 | B86: Jannatul Pramanik | C86: Nurul Howlader | D86: Female | E86: 44 | F86: Single | G86: Housewife | H86: HSC | I86: 17500 | J86: Unemployed | L86: Cox's Bazar | M86: Chattogram | N86: Own House | O86: 0 | P86: BR-07 | Q86: BPBL Jahaj Company Mor Branch | R86: Rangpur | S86: Rangpur | T86: BPBL-LN-2026-000085 | U86: Business Loan | V86: 300000 | W86: 15 | X86: 72 | Y86: 46202 | AB86: =ROUND(PMT(W86/1200,X86,-V86),2) -> 6343.5 | AC86: 439000 | AD86: 1 | AE86: 18100 | AF86: 10800 | AG86: 8 | AH86: 18200 | AI86: 630 | AJ86: =ROUND(AB86/I86,4) -> 0.3625 | AK86: =IF(AND(AI86>=750,AJ86<=0.35),"Low",IF(AND(AI86>=600,AJ86<=0.5),"Medium","High")) -> Medium | AL86: 2 | AM86: No | AO86: Rejected | AP86: 0.295
A87: BPBL-CUS-000086 | B87: Suraiya Gazi | C87: Jamal Akter | D87: Female | E87: 51 | F87: Single | H87: SSC | I87: 19000 | J87: Self-Employed | K87: 24 | L87: Natore | M87: Rajshahi | N87: Own House | O87: 0 | P87: BR-12 | Q87: BPBL Satmatha Branch | R87: Bogura | S87: Rajshahi | T87: BPBL-LN-2026-000086 | U87: Agricultural Loan | V87: 82000 | W87: 8.49 | X87: 12 | Y87: 46199 | Z87: 46205 | AA87: 46210 | AB87: =ROUND(PMT(W87/1200,X87,-V87),2) -> 7151.64 | AC87: 0 | AE87: 71800 | AF87: 27100 | AG87: 24 | AH87: 10300 | AI87: 667 | AJ87: =ROUND(AB87/I87,4) -> 0.3764 | AK87: =IF(AND(AI87>=750,AJ87<=0.35),"Low",IF(AND(AI87>=600,AJ87<=0.5),"Medium","High")) -> Medium | AL87: 3 | AM87: Yes | AN87: On Time | AO87: Approved | AP87: 0.368
A88: BPBL-CUS-000087 | B88: Robiul Karim | C88: Shamim Roy | D88: Male | E88: 25 | F88: Single | G88: Teacher | H88: Bachelor's | I88: 19000 | J88: Private | K88: 3 | L88: Lakshmipur | M88: Chattogram | N88: Rented House | O88: 0 | P88: BR-02 | Q88: BPBL Agrabad Branch | R88: Chattogram | S88: Chattogram | T88: BPBL-LN-2026-000087 | U88: Education Loan | V88: 105000 | W88: 10.27 | X88: 18 | Y88: 46185 | Z88: 46194 | AA88: 46200 | AB88: =ROUND(PMT(W88/1200,X88,-V88),2) -> 6319.05 | AC88: 0 | AD88: 1 | AE88: 67900 | AF88: 36300 | AG88: 44 | AH88: 18000 | AI88: 710 | AJ88: =ROUND(AB88/I88,4) -> 0.3326 | AK88: =IF(AND(AI88>=750,AJ88<=0.35),"Low",IF(AND(AI88>=600,AJ88<=0.5),"Medium","High")) -> Medium | AL88: 1 | AM88: No | AN88: On Time | AO88: Approved | AP88: 0.211
A89: BPBL-CUS-000088 | B89: Hossain Alam | C89: Asaduzzaman Uddin | D89: Male | E89: 30 | F89: Married | G89: Teacher | H89: Master's | I89: 58500 | J89: Private | K89: 2 | L89: Cox's Bazar | M89: Chattogram | N89: Family Owned | O89: 0 | P89: BR-15 | Q89: BPBL Maijdee Court Branch | R89: Noakhali | S89: Chattogram | T89: BPBL-LN-2026-000088 | U89: Home Loan | V89: 1200000 | W89: 11.23 | X89: 216 | Y89: 46191 | Z89: 46196 | AA89: 46201 | AB89: =ROUND(PMT(W89/1200,X89,-V89),2) -> 12963.49 | AC89: 1693000 | AD89: 0 | AE89: 153400 | AF89: 74000 | AG89: 39 | AH89: 25700 | AI89: 777 | AJ89: =ROUND(AB89/I89,4) -> 0.2216 | AK89: =IF(AND(AI89>=750,AJ89<=0.35),"Low",IF(AND(AI89>=600,AJ89<=0.5),"Medium","High")) -> Low | AL89: 0 | AM89: No | AN89: On Time | AO89: Approved | AP89: 0.152
A90: BPBL-CUS-000089 | B90: Mahmuda Mridha | C90: Bashir Sardar | D90: Female | E90: 21 | F90: Married | G90: Government Service | H90: HSC | I90: 32000 | J90: Government | K90: 0 | L90: Kushtia | M90: Khulna | N90: Family Owned | O90: 0 | P90: BR-03 | Q90: BPBL Sonadanga Branch | R90: Khulna | S90: Khulna | T90: BPBL-LN-2026-000089 | U90: Education Loan | V90: 382000 | W90: 8.9 | X90: 42 | Y90: 46189 | AB90: =ROUND(PMT(W90/1200,X90,-V90),2) -> 10618.66 | AC90: 0 | AD90: 0 | AE90: 40200 | AF90: 16500 | AG90: 16 | AH90: 26200 | AI90: 746 | AJ90: =ROUND(AB90/I90,4) -> 0.3318 | AK90: =IF(AND(AI90>=750,AJ90<=0.35),"Low",IF(AND(AI90>=600,AJ90<=0.5),"Medium","High")) -> Medium | AM90: No | AO90: Pending | AP90: 0.207
A91: BPBL-CUS-000090 | B91: Anwar Howlader | C91: Monir Karim | D91: Male | E91: 35 | F91: Married | G91: Government Service | H91: Bachelor's | I91: 70500 | J91: Government | K91: 8 | L91: Sherpur | M91: Mymensingh | N91: Rented House | O91: 0 | P91: BR-08 | Q91: BPBL Notun Bazar Branch | R91: Mymensingh | S91: Mymensingh | T91: BPBL-LN-2026-000090 | U91: Car Loan | V91: 895000 | W91: 9.97 | X91: 54 | Y91: 46201 | AB91: =ROUND(PMT(W91/1200,X91,-V91),2) -> 20636.76 | AC91: 923000 | AD91: 1 | AE91: 236100 | AF91: 96200 | AH91: 38400 | AI91: 673 | AJ91: =ROUND(AB91/I91,4) -> 0.2927 | AK91: =IF(AND(AI91>=750,AJ91<=0.35),"Low",IF(AND(AI91>=600,AJ91<=0.5),"Medium","High")) -> Medium | AL91: 1 | AM91: Yes | AO91: Rejected | AP91: 0.369
A92: BPBL-CUS-000091 | B92: Zubayer Alam | C92: Emdadul Pramanik | D92: Male | E92: 43 | F92: Married | G92: Farmer | H92: Below SSC | I92: 29000 | J92: Self-Employed | K92: 24 | L92: Kushtia | M92: Khulna | N92: Own House | O92: 1 | P92: BR-13 | Q92: BPBL M.K. Road Branch | R92: Jessore | S92: Khulna | T92: BPBL-LN-2026-000091 | U92: Business Loan | V92: 300000 | W92: 11.6 | X92: 42 | Y92: 46181 | AB92: =ROUND(PMT(W92/1200,X92,-V92),2) -> 8724.71 | AC92: 372000 | AD92: 1 | AE92: 68800 | AF92: 14300 | AG92: 33 | AH92: 9000 | AI92: 683 | AJ92: =ROUND(AB92/I92,4) -> 0.3009 | AK92: =IF(AND(AI92>=750,AJ92<=0.35),"Low",IF(AND(AI92>=600,AJ92<=0.5),"Medium","High")) -> Medium | AL92: 3 | AM92: No | AO92: Pending | AP92: 0.26
A93: BPBL-CUS-000092 | B93: Kulsum Saha | C93: Delwar Hawlader | D93: Female | E93: 27 | F93: Married | G93: Doctor | H93: Master's | I93: 135500 | J93: Self-Employed | K93: 2 | L93: Noakhali | M93: Chattogram | N93: Own House | O93: 3 | P93: BR-15 | Q93: BPBL Maijdee Court Branch | R93: Noakhali | S93: Chattogram | T93: BPBL-LN-2026-000092 | U93: Education Loan | V93: 1318000 | W93: 8.76 | X93: 48 | Y93: 46181 | Z93: 46187 | AA93: 46188 | AB93: =ROUND(PMT(W93/1200,X93,-V93),2) -> 32648.49 | AC93: 0 | AD93: 0 | AE93: 520800 | AF93: 257000 | AG93: 30 | AH93: 74800 | AI93: 670 | AJ93: =ROUND(AB93/I93,4) -> 0.2409 | AK93: =IF(AND(AI93>=750,AJ93<=0.35),"Low",IF(AND(AI93>=600,AJ93<=0.5),"Medium","High")) -> Medium | AL93: 2 | AM93: No | AN93: On Time | AO93: Approved | AP93: 0.291
A94: BPBL-CUS-000093 | B94: Shapla Chowdhury | C94: Jamal Khan | D94: Female | E94: 31 | F94: Single | G94: Self-Employed | H94: SSC | I94: 49500 | J94: Self-Employed | K94: 6 | L94: Manikganj | M94: Dhaka | N94: Own House | O94: 0 | P94: BR-01 | Q94: BPBL Gulshan Branch | R94: Dhaka | S94: Dhaka | T94: BPBL-LN-2026-000093 | U94: SME Loan | V94: 350000 | W94: 12.95 | X94: 18 | Y94: 46182 | AB94: =ROUND(PMT(W94/1200,X94,-V94),2) -> 21498.49 | AC94: 441000 | AD94: 1 | AE94: 113500 | AF94: 50000 | AG94: 18 | AH94: 16500 | AI94: 701 | AJ94: =ROUND(AB94/I94,4) -> 0.4343 | AK94: =IF(AND(AI94>=750,AJ94<=0.35),"Low",IF(AND(AI94>=600,AJ94<=0.5),"Medium","High")) -> Medium | AL94: 3 | AM94: No | AO94: Rejected | AP94: 0.284
A95: BPBL-CUS-000094 | B95: Shapla Pramanik | C95: Mizanur Khondkar | D95: Female | E95: 40 | F95: Married | G95: Farmer | H95: Below SSC | I95: 12500 | J95: Self-Employed | K95: 21 | L95: Thakurgaon | M95: Rangpur | N95: Rented House | O95: 0 | P95: BR-07 | Q95: BPBL Jahaj Company Mor Branch | R95: Rangpur | S95: Rangpur | T95: BPBL-LN-2026-000094 | U95: Agricultural Loan | V95: 132000 | W95: 9.97 | X95: 24 | Y95: 46178 | Z95: 46187 | AA95: 46189 | AB95: =ROUND(PMT(W95/1200,X95,-V95),2) -> 6089.3 | AC95: 0 | AD95: 0 | AE95: 10600 | AF95: 4600 | AG95: 21 | AH95: 11400 | AI95: 640 | AJ95: =ROUND(AB95/I95,4) -> 0.4871 | AK95: =IF(AND(AI95>=750,AJ95<=0.35),"Low",IF(AND(AI95>=600,AJ95<=0.5),"Medium","High")) -> Medium | AL95: 1 | AM95: No | AN95: On Time | AO95: Approved | AP95: 0.275
A96: BPBL-CUS-000095 | B96: Bashir Faruqui | C96: Nazrul Islam | D96: Male | E96: 48 | F96: Single | G96: Doctor | H96: PhD | I96: 183500 | J96: Self-Employed | K96: 23 | L96: Narayanganj | M96: Dhaka | N96: Family Owned | O96: 0 | P96: BR-10 | Q96: BPBL Chashara Branch | R96: Narayanganj | S96: Dhaka | T96: BPBL-LN-2026-000095 | U96: Car Loan | V96: 3000000 | W96: 9.63 | X96: 72 | Y96: 46187 | Z96: 46188 | AA96: 46193 | AB96: =ROUND(PMT(W96/1200,X96,-V96),2) -> 55019.39 | AC96: 4198000 | AD96: 0 | AE96: 572200 | AF96: 289500 | AG96: 53 | AH96: 151400 | AI96: 716 | AJ96: =ROUND(AB96/I96,4) -> 0.2998 | AK96: =IF(AND(AI96>=750,AJ96<=0.35),"Low",IF(AND(AI96>=600,AJ96<=0.5),"Medium","High")) -> Medium | AL96: 3 | AM96: No | AN96: On Time | AO96: Approved | AP96: 0.31
A97: BPBL-CUS-000096 | B97: Nodi Islam | C97: Masud Karim | D97: Female | E97: 33 | F97: Married | G97: Business Owner | H97: Bachelor's | I97: 64000 | J97: Business | K97: 13 | L97: Kishoreganj | M97: Dhaka | N97: Own House | O97: 2 | P97: BR-10 | Q97: BPBL Chashara Branch | R97: Narayanganj | S97: Dhaka | T97: BPBL-LN-2026-000096 | U97: SME Loan | V97: 247000 | W97: 10.49 | X97: 24 | Y97: 46196 | Z97: 46205 | AA97: 46210 | AB97: =ROUND(PMT(W97/1200,X97,-V97),2) -> 11453.74 | AC97: 357000 | AD97: 0 | AE97: 214800 | AF97: 114000 | AG97: 40 | AH97: 62500 | AI97: 900 | AJ97: =ROUND(AB97/I97,4) -> 0.179 | AK97: =IF(AND(AI97>=750,AJ97<=0.35),"Low",IF(AND(AI97>=600,AJ97<=0.5),"Medium","High")) -> Low | AM97: No | AN97: Delayed | AO97: Approved | AP97: 0.01
A98: BPBL-CUS-000097 | B98: Shirin Patwary | C98: Golam Sardar | D98: Female | E98: 36 | F98: Married | G98: Private Service | H98: Master's | I98: 71000 | J98: Private | K98: 11 | L98: Gazipur | M98: Dhaka | N98: Rented House | O98: 4 | P98: BR-09 | Q98: BPBL Chandona Chowrasta Branch | R98: Gazipur | S98: Dhaka | T98: BPBL-LN-2026-000097 | U98: Business Loan | V98: 493000 | W98: 12.19 | X98: 24 | Y98: 46199 | Z98: 46209 | AA98: 46213 | AB98: =ROUND(PMT(W98/1200,X98,-V98),2) -> 23250.99 | AC98: 672000 | AD98: 1 | AE98: 161200 | AF98: 83900 | AG98: 36 | AH98: 62900 | AI98: 755 | AJ98: =ROUND(AB98/I98,4) -> 0.3275 | AK98: =IF(AND(AI98>=750,AJ98<=0.35),"Low",IF(AND(AI98>=600,AJ98<=0.5),"Medium","High")) -> Low | AL98: 1 | AM98: No | AN98: On Time | AO98: Approved | AP98: 0.166
A99: BPBL-CUS-000098 | B99: Promi Uddin | C99: Delwar Hossain | D99: Female | E99: 63 | F99: Single | G99: Farmer | H99: HSC | I99: 32500 | J99: Self-Employed | K99: 39 | L99: Habiganj | M99: Sylhet | N99: Own House | O99: 0 | P99: BR-04 | Q99: BPBL Shaheb Bazar Branch | R99: Rajshahi | S99: Rajshahi | T99: BPBL-LN-2026-000098 | U99: Agricultural Loan | V99: 137000 | W99: 9.28 | X99: 12 | Y99: 46186 | AB99: =ROUND(PMT(W99/1200,X99,-V99),2) -> 11998.65 | AC99: 0 | AD99: 0 | AE99: 44300 | AF99: 20500 | AG99: 27 | AH99: 35500 | AI99: 900 | AJ99: =ROUND(AB99/I99,4) -> 0.3692 | AK99: =IF(AND(AI99>=750,AJ99<=0.35),"Low",IF(AND(AI99>=600,AJ99<=0.5),"Medium","High")) -> Medium | AL99: 1 | AM99: No | AO99: Rejected | AP99: 0.044
A100: BPBL-CUS-000099 | B100: Tasnim Khan | C100: Ekram Biswas | D100: Female | E100: 35 | F100: Single | G100: Private Service | H100: Master's | I100: 50500 | J100: Private | K100: 11 | L100: Brahmanbaria | M100: Chattogram | N100: Own House | O100: 1 | P100: BR-05 | Q100: BPBL Zindabazar Branch | R100: Sylhet | S100: Sylhet | T100: BPBL-LN-2026-000099 | U100: Education Loan | V100: 229000 | W100: 10.04 | X100: 12 | Y100: 46181 | Z100: 46190 | AA100: 46192 | AB100: =ROUND(PMT(W100/1200,X100,-V100),2) -> 20137 | AC100: 0 | AD100: 1 | AE100: 194600 | AF100: 55300 | AG100: 37 | AH100: 28400 | AI100: 598 | AJ100: =ROUND(AB100/I100,4) -> 0.3988 | AK100: =IF(AND(AI100>=750,AJ100<=0.35),"Low",IF(AND(AI100>=600,AJ100<=0.5),"Medium","High")) -> High | AL100: 3 | AM100: No | AN100: Delayed | AO100: Approved | AP100: 0.328
...

Sheet Branch_Summary
A1: Branch_ID | B1: Branch_Name | C1: Branch_City | D1: Branch_Division | E1: Total_Applications | F1: Approved_Count | G1: Rejected_Count | H1: Pending_Count | I1: Closed_Count | J1: Approval_Rate | K1: Total_Loan_Amount_Disbursed | L1: Average_Loan_Amount | M1: Average_Credit_Score | N1: Average_Interest_Rate | O1: Missed_Payment_Rate
A2: BR-01 | B2: BPBL Gulshan Branch | C2: Dhaka | D2: Dhaka | E2: =COUNTIF(Loan_Data!$P$2:$P$801,$A2) -> 56 | F2: =COUNTIFS(Loan_Data!$P$2:$P$801,$A2,Loan_Data!$AO$2:$AO$801,"Approved") -> 33 | G2: =COUNTIFS(Loan_Data!$P$2:$P$801,$A2,Loan_Data!$AO$2:$AO$801,"Rejected") -> 8 | H2: =COUNTIFS(Loan_Data!$P$2:$P$801,$A2,Loan_Data!$AO$2:$AO$801,"Pending") -> 12 | I2: =COUNTIFS(Loan_Data!$P$2:$P$801,$A2,Loan_Data!$AO$2:$AO$801,"Closed") -> 3 | J2: =IFERROR((F2+I2)/E2,0) -> 0.64285714 | K2: =SUMIFS(Loan_Data!$V$2:$V$801,Loan_Data!$P$2:$P$801,$A2,Loan_Data!$AO$2:$AO$801,"Approved")+SUMIFS(Loan_Data!$V$2:$V$801,Loan_Data!$P$2:$P$801,$A2,Loan_Data!$AO$2:$AO$801,"Closed") -> 21021000 | L2: =IFERROR(K2/(F2+I2),0) -> 583916.67 | M2: =IFERROR(AVERAGEIF(Loan_Data!$P$2:$P$801,$A2,Loan_Data!$AI$2:$AI$801),0) -> 727.39286 | N2: =IFERROR(AVERAGEIF(Loan_Data!$P$2:$P$801,$A2,Loan_Data!$W$2:$W$801),0) -> 11.508393 | O2: =IFERROR(COUNTIFS(Loan_Data!$P$2:$P$801,$A2,Loan_Data!$AN$2:$AN$801,"Missed Payment")/(F2+I2),0) -> 0.13888889
A3: BR-02 | B3: BPBL Agrabad Branch | C3: Chattogram | D3: Chattogram | E3: =COUNTIF(Loan_Data!$P$2:$P$801,$A3) -> 56 | F3: =COUNTIFS(Loan_Data!$P$2:$P$801,$A3,Loan_Data!$AO$2:$AO$801,"Approved") -> 29 | G3: =COUNTIFS(Loan_Data!$P$2:$P$801,$A3,Loan_Data!$AO$2:$AO$801,"Rejected") -> 9 | H3: =COUNTIFS(Loan_Data!$P$2:$P$801,$A3,Loan_Data!$AO$2:$AO$801,"Pending") -> 14 | I3: =COUNTIFS(Loan_Data!$P$2:$P$801,$A3,Loan_Data!$AO$2:$AO$801,"Closed") -> 4 | J3: =IFERROR((F3+I3)/E3,0) -> 0.58928571 | K3: =SUMIFS(Loan_Data!$V$2:$V$801,Loan_Data!$P$2:$P$801,$A3,Loan_Data!$AO$2:$AO$801,"Approved")+SUMIFS(Loan_Data!$V$2:$V$801,Loan_Data!$P$2:$P$801,$A3,Loan_Data!$AO$2:$AO$801,"Closed") -> 22551408 | L3: =IFERROR(K3/(F3+I3),0) -> 683376 | M3: =IFERROR(AVERAGEIF(Loan_Data!$P$2:$P$801,$A3,Loan_Data!$AI$2:$AI$801),0) -> 738.08929 | N3: =IFERROR(AVERAGEIF(Loan_Data!$P$2:$P$801,$A3,Loan_Data!$W$2:$W$801),0) -> 11.382143 | O3: =IFERROR(COUNTIFS(Loan_Data!$P$2:$P$801,$A3,Loan_Data!$AN$2:$AN$801,"Missed Payment")/(F3+I3),0) -> 0.060606061
A4: BR-03 | B4: BPBL Sonadanga Branch | C4: Khulna | D4: Khulna | E4: =COUNTIF(Loan_Data!$P$2:$P$801,$A4) -> 50 | F4: =COUNTIFS(Loan_Data!$P$2:$P$801,$A4,Loan_Data!$AO$2:$AO$801,"Approved") -> 32 | G4: =COUNTIFS(Loan_Data!$P$2:$P$801,$A4,Loan_Data!$AO$2:$AO$801,"Rejected") -> 9 | H4: =COUNTIFS(Loan_Data!$P$2:$P$801,$A4,Loan_Data!$AO$2:$AO$801,"Pending") -> 6 | I4: =COUNTIFS(Loan_Data!$P$2:$P$801,$A4,Loan_Data!$AO$2:$AO$801,"Closed") -> 3 | J4: =IFERROR((F4+I4)/E4,0) -> 0.7 | K4: =SUMIFS(Loan_Data!$V$2:$V$801,Loan_Data!$P$2:$P$801,$A4,Loan_Data!$AO$2:$AO$801,"Approved")+SUMIFS(Loan_Data!$V$2:$V$801,Loan_Data!$P$2:$P$801,$A4,Loan_Data!$AO$2:$AO$801,"Closed") -> 33174847 | L4: =IFERROR(K4/(F4+I4),0) -> 947852.77 | M4: =IFERROR(AVERAGEIF(Loan_Data!$P$2:$P$801,$A4,Loan_Data!$AI$2:$AI$801),0) -> 712.22 | N4: =IFERROR(AVERAGEIF(Loan_Data!$P$2:$P$801,$A4,Loan_Data!$W$2:$W$801),0) -> 10.7556 | O4: =IFERROR(COUNTIFS(Loan_Data!$P$2:$P$801,$A4,Loan_Data!$AN$2:$AN$801,"Missed Payment")/(F4+I4),0) -> 0.085714286
A5: BR-04 | B5: BPBL Shaheb Bazar Branch | C5: Rajshahi | D5: Rajshahi | E5: =COUNTIF(Loan_Data!$P$2:$P$801,$A5) -> 46 | F5: =COUNTIFS(Loan_Data!$P$2:$P$801,$A5,Loan_Data!$AO$2:$AO$801,"Approved") -> 27 | G5: =COUNTIFS(Loan_Data!$P$2:$P$801,$A5,Loan_Data!$AO$2:$AO$801,"Rejected") -> 5 | H5: =COUNTIFS(Loan_Data!$P$2:$P$801,$A5,Loan_Data!$AO$2:$AO$801,"Pending") -> 9 | I5: =COUNTIFS(Loan_Data!$P$2:$P$801,$A5,Loan_Data!$AO$2:$AO$801,"Closed") -> 5 | J5: =IFERROR((F5+I5)/E5,0) -> 0.69565217 | K5: =SUMIFS(Loan_Data!$V$2:$V$801,Loan_Data!$P$2:$P$801,$A5,Loan_Data!$AO$2:$AO$801,"Approved")+SUMIFS(Loan_Data!$V$2:$V$801,Loan_Data!$P$2:$P$801,$A5,Loan_Data!$AO$2:$AO$801,"Closed") -> 26347000 | L5: =IFERROR(K5/(F5+I5),0) -> 823343.75 | M5: =IFERROR(AVERAGEIF(Loan_Data!$P$2:$P$801,$A5,Loan_Data!$AI$2:$AI$801),0) -> 720.34783 | N5: =IFERROR(AVERAGEIF(Loan_Data!$P$2:$P$801,$A5,Loan_Data!$W$2:$W$801),0) -> 11.328043 | O5: =IFERROR(COUNTIFS(Loan_Data!$P$2:$P$801,$A5,Loan_Data!$AN$2:$AN$801,"Missed Payment")/(F5+I5),0) -> 0.09375
A6: BR-05 | B6: BPBL Zindabazar Branch | C6: Sylhet | D6: Sylhet | E6: =COUNTIF(Loan_Data!$P$2:$P$801,$A6) -> 51 | F6: =COUNTIFS(Loan_Data!$P$2:$P$801,$A6,Loan_Data!$AO$2:$AO$801,"Approved") -> 35 | G6: =COUNTIFS(Loan_Data!$P$2:$P$801,$A6,Loan_Data!$AO$2:$AO$801,"Rejected") -> 4 | H6: =COUNTIFS(Loan_Data!$P$2:$P$801,$A6,Loan_Data!$AO$2:$AO$801,"Pending") -> 6 | I6: =COUNTIFS(Loan_Data!$P$2:$P$801,$A6,Loan_Data!$AO$2:$AO$801,"Closed") -> 6 | J6: =IFERROR((F6+I6)/E6,0) -> 0.80392157 | K6: =SUMIFS(Loan_Data!$V$2:$V$801,Loan_Data!$P$2:$P$801,$A6,Loan_Data!$AO$2:$AO$801,"Approved")+SUMIFS(Loan_Data!$V$2:$V$801,Loan_Data!$P$2:$P$801,$A6,Loan_Data!$AO$2:$AO$801,"Closed") -> 37871092 | L6: =IFERROR(K6/(F6+I6),0) -> 923685.17 | M6: =IFERROR(AVERAGEIF(Loan_Data!$P$2:$P$801,$A6,Loan_Data!$AI$2:$AI$801),0) -> 683.58824 | N6: =IFERROR(AVERAGEIF(Loan_Data!$P$2:$P$801,$A6,Loan_Data!$W$2:$W$801),0) -> 11.452157 | O6: =IFERROR(COUNTIFS(Loan_Data!$P$2:$P$801,$A6,Loan_Data!$AN$2:$AN$801,"Missed Payment")/(F6+I6),0) -> 0.073170732
A7: BR-06 | B7: BPBL Sadar Road Branch | C7: Barishal | D7: Barishal | E7: =COUNTIF(Loan_Data!$P$2:$P$801,$A7) -> 59 | F7: =COUNTIFS(Loan_Data!$P$2:$P$801,$A7,Loan_Data!$AO$2:$AO$801,"Approved") -> 37 | G7: =COUNTIFS(Loan_Data!$P$2:$P$801,$A7,Loan_Data!$AO$2:$AO$801,"Rejected") -> 11 | H7: =COUNTIFS(Loan_Data!$P$2:$P$801,$A7,Loan_Data!$AO$2:$AO$801,"Pending") -> 4 | I7: =COUNTIFS(Loan_Data!$P$2:$P$801,$A7,Loan_Data!$AO$2:$AO$801,"Closed") -> 7 | J7: =IFERROR((F7+I7)/E7,0) -> 0.74576271 | K7: =SUMIFS(Loan_Data!$V$2:$V$801,Loan_Data!$P$2:$P$801,$A7,Loan_Data!$AO$2:$AO$801,"Approved")+SUMIFS(Loan_Data!$V$2:$V$801,Loan_Data!$P$2:$P$801,$A7,Loan_Data!$AO$2:$AO$801,"Closed") -> 35382000 | L7: =IFERROR(K7/(F7+I7),0) -> 804136.36 | M7: =IFERROR(AVERAGEIF(Loan_Data!$P$2:$P$801,$A7,Loan_Data!$AI$2:$AI$801),0) -> 719.50847 | N7: =IFERROR(AVERAGEIF(Loan_Data!$P$2:$P$801,$A7,Loan_Data!$W$2:$W$801),0) -> 11.256102 | O7: =IFERROR(COUNTIFS(Loan_Data!$P$2:$P$801,$A7,Loan_Data!$AN$2:$AN$801,"Missed Payment")/(F7+I7),0) -> 0.13636364
A8: BR-07 | B8: BPBL Jahaj Company Mor Branch | C8: Rangpur | D8: Rangpur | E8: =COUNTIF(Loan_Data!$P$2:$P$801,$A8) -> 57 | F8: =COUNTIFS(Loan_Data!$P$2:$P$801,$A8,Loan_Data!$AO$2:$AO$801,"Approved") -> 36 | G8: =COUNTIFS(Loan_Data!$P$2:$P$801,$A8,Loan_Data!$AO$2:$AO$801,"Rejected") -> 11 | H8: =COUNTIFS(Loan_Data!$P$2:$P$801,$A8,Loan_Data!$AO$2:$AO$801,"Pending") -> 8 | I8: =COUNTIFS(Loan_Data!$P$2:$P$801,$A8,Loan_Data!$AO$2:$AO$801,"Closed") -> 2 | J8: =IFERROR((F8+I8)/E8,0) -> 0.66666667 | K8: =SUMIFS(Loan_Data!$V$2:$V$801,Loan_Data!$P$2:$P$801,$A8,Loan_Data!$AO$2:$AO$801,"Approved")+SUMIFS(Loan_Data!$V$2:$V$801,Loan_Data!$P$2:$P$801,$A8,Loan_Data!$AO$2:$AO$801,"Closed") -> 23437000 | L8: =IFERROR(K8/(F8+I8),0) -> 616763.16 | M8: =IFERROR(AVERAGEIF(Loan_Data!$P$2:$P$801,$A8,Loan_Data!$AI$2:$AI$801),0) -> 728.64912 | N8: =IFERROR(AVERAGEIF(Loan_Data!$P$2:$P$801,$A8,Loan_Data!$W$2:$W$801),0) -> 11.434737 | O8: =IFERROR(COUNTIFS(Loan_Data!$P$2:$P$801,$A8,Loan_Data!$AN$2:$AN$801,"Missed Payment")/(F8+I8),0) -> 0.078947368
A9: BR-08 | B9: BPBL Notun Bazar Branch | C9: Mymensingh | D9: Mymensingh | E9: =COUNTIF(Loan_Data!$P$2:$P$801,$A9) -> 48 | F9: =COUNTIFS(Loan_Data!$P$2:$P$801,$A9,Loan_Data!$AO$2:$AO$801,"Approved") -> 26 | G9: =COUNTIFS(Loan_Data!$P$2:$P$801,$A9,Loan_Data!$AO$2:$AO$801,"Rejected") -> 8 | H9: =COUNTIFS(Loan_Data!$P$2:$P$801,$A9,Loan_Data!$AO$2:$AO$801,"Pending") -> 10 | I9: =COUNTIFS(Loan_Data!$P$2:$P$801,$A9,Loan_Data!$AO$2:$AO$801,"Closed") -> 4 | J9: =IFERROR((F9+I9)/E9,0) -> 0.625 | K9: =SUMIFS(Loan_Data!$V$2:$V$801,Loan_Data!$P$2:$P$801,$A9,Loan_Data!$AO$2:$AO$801,"Approved")+SUMIFS(Loan_Data!$V$2:$V$801,Loan_Data!$P$2:$P$801,$A9,Loan_Data!$AO$2:$AO$801,"Closed") -> 16662000 | L9: =IFERROR(K9/(F9+I9),0) -> 555400 | M9: =IFERROR(AVERAGEIF(Loan_Data!$P$2:$P$801,$A9,Loan_Data!$AI$2:$AI$801),0) -> 689.45833 | N9: =IFERROR(AVERAGEIF(Loan_Data!$P$2:$P$801,$A9,Loan_Data!$W$2:$W$801),0) -> 11.199583 | O9: =IFERROR(COUNTIFS(Loan_Data!$P$2:$P$801,$A9,Loan_Data!$AN$2:$AN$801,"Missed Payment")/(F9+I9),0) -> 0.16666667
A10: BR-09 | B10: BPBL Chandona Chowrasta Branch | C10: Gazipur | D10: Dhaka | E10: =COUNTIF(Loan_Data!$P$2:$P$801,$A10) -> 44 | F10: =COUNTIFS(Loan_Data!$P$2:$P$801,$A10,Loan_Data!$AO$2:$AO$801,"Approved") -> 26 | G10: =COUNTIFS(Loan_Data!$P$2:$P$801,$A10,Loan_Data!$AO$2:$AO$801,"Rejected") -> 9 | H10: =COUNTIFS(Loan_Data!$P$2:$P$801,$A10,Loan_Data!$AO$2:$AO$801,"Pending") -> 5 | I10: =COUNTIFS(Loan_Data!$P$2:$P$801,$A10,Loan_Data!$AO$2:$AO$801,"Closed") -> 4 | J10: =IFERROR((F10+I10)/E10,0) -> 0.68181818 | K10: =SUMIFS(Loan_Data!$V$2:$V$801,Loan_Data!$P$2:$P$801,$A10,Loan_Data!$AO$2:$AO$801,"Approved")+SUMIFS(Loan_Data!$V$2:$V$801,Loan_Data!$P$2:$P$801,$A10,Loan_Data!$AO$2:$AO$801,"Closed") -> 27697563 | L10: =IFERROR(K10/(F10+I10),0) -> 923252.1 | M10: =IFERROR(AVERAGEIF(Loan_Data!$P$2:$P$801,$A10,Loan_Data!$AI$2:$AI$801),0) -> 717.63636 | N10: =IFERROR(AVERAGEIF(Loan_Data!$P$2:$P$801,$A10,Loan_Data!$W$2:$W$801),0) -> 10.917727 | O10: =IFERROR(COUNTIFS(Loan_Data!$P$2:$P$801,$A10,Loan_Data!$AN$2:$AN$801,"Missed Payment")/(F10+I10),0) -> 0.1
A11: BR-10 | B11: BPBL Chashara Branch | C11: Narayanganj | D11: Dhaka | E11: =COUNTIF(Loan_Data!$P$2:$P$801,$A11) -> 57 | F11: =COUNTIFS(Loan_Data!$P$2:$P$801,$A11,Loan_Data!$AO$2:$AO$801,"Approved") -> 40 | G11: =COUNTIFS(Loan_Data!$P$2:$P$801,$A11,Loan_Data!$AO$2:$AO$801,"Rejected") -> 7 | H11: =COUNTIFS(Loan_Data!$P$2:$P$801,$A11,Loan_Data!$AO$2:$AO$801,"Pending") -> 10 | I11: =COUNTIFS(Loan_Data!$P$2:$P$801,$A11,Loan_Data!$AO$2:$AO$801,"Closed") -> 0 | J11: =IFERROR((F11+I11)/E11,0) -> 0.70175439 | K11: =SUMIFS(Loan_Data!$V$2:$V$801,Loan_Data!$P$2:$P$801,$A11,Loan_Data!$AO$2:$AO$801,"Approved")+SUMIFS(Loan_Data!$V$2:$V$801,Loan_Data!$P$2:$P$801,$A11,Loan_Data!$AO$2:$AO$801,"Closed") -> 32822000 | L11: =IFERROR(K11/(F11+I11),0) -> 820550 | M11: =IFERROR(AVERAGEIF(Loan_Data!$P$2:$P$801,$A11,Loan_Data!$AI$2:$AI$801),0) -> 715.15789 | N11: =IFERROR(AVERAGEIF(Loan_Data!$P$2:$P$801,$A11,Loan_Data!$W$2:$W$801),0) -> 11.304912 | O11: =IFERROR(COUNTIFS(Loan_Data!$P$2:$P$801,$A11,Loan_Data!$AN$2:$AN$801,"Missed Payment")/(F11+I11),0) -> 0.05
A12: BR-11 | B12: BPBL Kandirpar Branch | C12: Cumilla | D12: Chattogram | E12: =COUNTIF(Loan_Data!$P$2:$P$801,$A12) -> 43 | F12: =COUNTIFS(Loan_Data!$P$2:$P$801,$A12,Loan_Data!$AO$2:$AO$801,"Approved") -> 26 | G12: =COUNTIFS(Loan_Data!$P$2:$P$801,$A12,Loan_Data!$AO$2:$AO$801,"Rejected") -> 7 | H12: =COUNTIFS(Loan_Data!$P$2:$P$801,$A12,Loan_Data!$AO$2:$AO$801,"Pending") -> 8 | I12: =COUNTIFS(Loan_Data!$P$2:$P$801,$A12,Loan_Data!$AO$2:$AO$801,"Closed") -> 2 | J12: =IFERROR((F12+I12)/E12,0) -> 0.65116279 | K12: =SUMIFS(Loan_Data!$V$2:$V$801,Loan_Data!$P$2:$P$801,$A12,Loan_Data!$AO$2:$AO$801,"Approved")+SUMIFS(Loan_Data!$V$2:$V$801,Loan_Data!$P$2:$P$801,$A12,Loan_Data!$AO$2:$AO$801,"Closed") -> 20701000 | L12: =IFERROR(K12/(F12+I12),0) -> 739321.43 | M12: =IFERROR(AVERAGEIF(Loan_Data!$P$2:$P$801,$A12,Loan_Data!$AI$2:$AI$801),0) -> 725.60465 | N12: =IFERROR(AVERAGEIF(Loan_Data!$P$2:$P$801,$A12,Loan_Data!$W$2:$W$801),0) -> 11.048372 | O12: =IFERROR(COUNTIFS(Loan_Data!$P$2:$P$801,$A12,Loan_Data!$AN$2:$AN$801,"Missed Payment")/(F12+I12),0) -> 0.14285714
A13: BR-12 | B13: BPBL Satmatha Branch | C13: Bogura | D13: Rajshahi | E13: =COUNTIF(Loan_Data!$P$2:$P$801,$A13) -> 67 | F13: =COUNTIFS(Loan_Data!$P$2:$P$801,$A13,Loan_Data!$AO$2:$AO$801,"Approved") -> 38 | G13: =COUNTIFS(Loan_Data!$P$2:$P$801,$A13,Loan_Data!$AO$2:$AO$801,"Rejected") -> 14 | H13: =COUNTIFS(Loan_Data!$P$2:$P$801,$A13,Loan_Data!$AO$2:$AO$801,"Pending") -> 9 | I13: =COUNTIFS(Loan_Data!$P$2:$P$801,$A13,Loan_Data!$AO$2:$AO$801,"Closed") -> 6 | J13: =IFERROR((F13+I13)/E13,0) -> 0.65671642 | K13: =SUMIFS(Loan_Data!$V$2:$V$801,Loan_Data!$P$2:$P$801,$A13,Loan_Data!$AO$2:$AO$801,"Approved")+SUMIFS(Loan_Data!$V$2:$V$801,Loan_Data!$P$2:$P$801,$A13,Loan_Data!$AO$2:$AO$801,"Closed") -> 38943552 | L13: =IFERROR(K13/(F13+I13),0) -> 885080.73 | M13: =IFERROR(AVERAGEIF(Loan_Data!$P$2:$P$801,$A13,Loan_Data!$AI$2:$AI$801),0) -> 722.34328 | N13: =IFERROR(AVERAGEIF(Loan_Data!$P$2:$P$801,$A13,Loan_Data!$W$2:$W$801),0) -> 11.041642 | O13: =IFERROR(COUNTIFS(Loan_Data!$P$2:$P$801,$A13,Loan_Data!$AN$2:$AN$801,"Missed Payment")/(F13+I13),0) -> 0.045454545
... A16: BR-15 | B16: BPBL Maijdee Court Branch | C16: Noakhali | D16: Chattogram | E16: =COUNTIF(Loan_Data!$P$2:$P$801,$A16) -> 52 | F16: =COUNTIFS(Loan_Data!$P$2:$P$801,$A16,Loan_Data!$AO$2:$AO$801,"Approved") -> 31 | G16: =COUNTIFS(Loan_Data!$P$2:$P$801,$A16,Loan_Data!$AO$2:$AO$801,"Rejected") -> 8 | H16: =COUNTIFS(Loan_Data!$P$2:$P$801,$A16,Loan_Data!$AO$2:$AO$801,"Pending") -> 10 | I16: =COUNTIFS(Loan_Data!$P$2:$P$801,$A16,Loan_Data!$AO$2:$AO$801,"Closed") -> 3 | J16: =IFERROR((F16+I16)/E16,0) -> 0.65384615 | K16: =SUMIFS(Loan_Data!$V$2:$V$801,Loan_Data!$P$2:$P$801,$A16,Loan_Data!$AO$2:$AO$801,"Approved")+SUMIFS(Loan_Data!$V$2:$V$801,Loan_Data!$P$2:$P$801,$A16,Loan_Data!$AO$2:$AO$801,"Closed") -> 27393000 | L16: =IFERROR(K16/(F16+I16),0) -> 805676.47 | M16: =IFERROR(AVERAGEIF(Loan_Data!$P$2:$P$801,$A16,Loan_Data!$AI$2:$AI$801),0) -> 703.30769 | N16: =IFERROR(AVERAGEIF(Loan_Data!$P$2:$P$801,$A16,Loan_Data!$W$2:$W$801),0) -> 11.354231 | O16: =IFERROR(COUNTIFS(Loan_Data!$P$2:$P$801,$A16,Loan_Data!$AN$2:$AN$801,"Missed Payment")/(F16+I16),0) -> 0.14705882
A17: TOTAL / OVERALL | E17: =SUM(E2:E16) -> 800 | F17: =SUM(F2:F16) -> 480 | G17: =SUM(G2:G16) -> 134 | H17: =SUM(H2:H16) -> 126 | I17: =SUM(I2:I16) -> 60 | J17: =IFERROR((F17+I17)/E17,0) -> 0.675 | K17: =SUM(K2:K16) -> 416564462 | L17: =IFERROR(K17/(F17+I17),0) -> 771415.67 | M17: =AVERAGE(M2:M16) -> 715.80272 | N17: =AVERAGE(N2:N16) -> 11.280255 | O17: =IFERROR(SUMPRODUCT(O2:O16,(F2:F16+I2:I16))/(F17+I17),0) -> 0.094444444

Sheet Loan_Type_Summary
A1: Loan_Type | B1: Total_Applications | C1: Approved_Count | D1: Rejected_Count | E1: Pending_Count | F1: Closed_Count | G1: Approval_Rate | H1: Total_Loan_Amount_Disbursed | I1: Average_Loan_Amount | J1: Average_Interest_Rate | K1: Average_Loan_Term_Months | L1: Average_EMI_Amount | M1: Average_DTI | N1: Average_Credit_Score | O1: Missed_Payment_Rate
A2: Agricultural Loan | B2: =COUNTIF(Loan_Data!$U$2:$U$801,$A2) -> 161 | C2: =COUNTIFS(Loan_Data!$U$2:$U$801,$A2,Loan_Data!$AO$2:$AO$801,"Approved") -> 93 | D2: =COUNTIFS(Loan_Data!$U$2:$U$801,$A2,Loan_Data!$AO$2:$AO$801,"Rejected") -> 29 | E2: =COUNTIFS(Loan_Data!$U$2:$U$801,$A2,Loan_Data!$AO$2:$AO$801,"Pending") -> 25 | F2: =COUNTIFS(Loan_Data!$U$2:$U$801,$A2,Loan_Data!$AO$2:$AO$801,"Closed") -> 14 | G2: =IFERROR((C2+F2)/B2,0) -> 0.66459627 | H2: =SUMIFS(Loan_Data!$V$2:$V$801,Loan_Data!$U$2:$U$801,$A2,Loan_Data!$AO$2:$AO$801,"Approved")+SUMIFS(Loan_Data!$V$2:$V$801,Loan_Data!$U$2:$U$801,$A2,Loan_Data!$AO$2:$AO$801,"Closed") -> 38406939 | I2: =IFERROR(H2/(C2+F2),0) -> 358943.36 | J2: =IFERROR(AVERAGEIF(Loan_Data!$U$2:$U$801,$A2,Loan_Data!$W$2:$W$801),0) -> 8.9537888 | K2: =IFERROR(AVERAGEIF(Loan_Data!$U$2:$U$801,$A2,Loan_Data!$X$2:$X$801),0) -> 20.161491 | L2: =IFERROR(AVERAGEIF(Loan_Data!$U$2:$U$801,$A2,Loan_Data!$AB$2:$AB$801),0) -> 18626.617 | M2: =IFERROR(AVERAGEIF(Loan_Data!$U$2:$U$801,$A2,Loan_Data!$AJ$2:$AJ$801),0) -> 0.52606584 | N2: =IFERROR(AVERAGEIF(Loan_Data!$U$2:$U$801,$A2,Loan_Data!$AI$2:$AI$801),0) -> 718.20497 | O2: =IFERROR(COUNTIFS(Loan_Data!$U$2:$U$801,$A2,Loan_Data!$AN$2:$AN$801,"Missed Payment")/(C2+F2),0) -> 0.08411215
A3: Business Loan | B3: =COUNTIF(Loan_Data!$U$2:$U$801,$A3) -> 115 | C3: =COUNTIFS(Loan_Data!$U$2:$U$801,$A3,Loan_Data!$AO$2:$AO$801,"Approved") -> 58 | D3: =COUNTIFS(Loan_Data!$U$2:$U$801,$A3,Loan_Data!$AO$2:$AO$801,"Rejected") -> 22 | E3: =COUNTIFS(Loan_Data!$U$2:$U$801,$A3,Loan_Data!$AO$2:$AO$801,"Pending") -> 20 | F3: =COUNTIFS(Loan_Data!$U$2:$U$801,$A3,Loan_Data!$AO$2:$AO$801,"Closed") -> 15 | G3: =IFERROR((C3+F3)/B3,0) -> 0.63478261 | H3: =SUMIFS(Loan_Data!$V$2:$V$801,Loan_Data!$U$2:$U$801,$A3,Loan_Data!$AO$2:$AO$801,"Approved")+SUMIFS(Loan_Data!$V$2:$V$801,Loan_Data!$U$2:$U$801,$A3,Loan_Data!$AO$2:$AO$801,"Closed") -> 59206000 | I3: =IFERROR(H3/(C3+F3),0) -> 811041.1 | J3: =IFERROR(AVERAGEIF(Loan_Data!$U$2:$U$801,$A3,Loan_Data!$W$2:$W$801),0) -> 13.958435 | K3: =IFERROR(AVERAGEIF(Loan_Data!$U$2:$U$801,$A3,Loan_Data!$X$2:$X$801),0) -> 50.13913 | L3: =IFERROR(AVERAGEIF(Loan_Data!$U$2:$U$801,$A3,Loan_Data!$AB$2:$AB$801),0) -> 22618.573 | M3: =IFERROR(AVERAGEIF(Loan_Data!$U$2:$U$801,$A3,Loan_Data!$AJ$2:$AJ$801),0) -> 0.38472522 | N3: =IFERROR(AVERAGEIF(Loan_Data!$U$2:$U$801,$A3,Loan_Data!$AI$2:$AI$801),0) -> 704.06957 | O3: =IFERROR(COUNTIFS(Loan_Data!$U$2:$U$801,$A3,Loan_Data!$AN$2:$AN$801,"Missed Payment")/(C3+F3),0) -> 0.054794521
A4: Car Loan | B4: =COUNTIF(Loan_Data!$U$2:$U$801,$A4) -> 123 | C4: =COUNTIFS(Loan_Data!$U$2:$U$801,$A4,Loan_Data!$AO$2:$AO$801,"Approved") -> 82 | D4: =COUNTIFS(Loan_Data!$U$2:$U$801,$A4,Loan_Data!$AO$2:$AO$801,"Rejected") -> 14 | E4: =COUNTIFS(Loan_Data!$U$2:$U$801,$A4,Loan_Data!$AO$2:$AO$801,"Pending") -> 21 | F4: =COUNTIFS(Loan_Data!$U$2:$U$801,$A4,Loan_Data!$AO$2:$AO$801,"Closed") -> 6 | G4: =IFERROR((C4+F4)/B4,0) -> 0.71544715 | H4: =SUMIFS(Loan_Data!$V$2:$V$801,Loan_Data!$U$2:$U$801,$A4,Loan_Data!$AO$2:$AO$801,"Approved")+SUMIFS(Loan_Data!$V$2:$V$801,Loan_Data!$U$2:$U$801,$A4,Loan_Data!$AO$2:$AO$801,"Closed") -> 67399563 | I4: =IFERROR(H4/(C4+F4),0) -> 765904.12 | J4: =IFERROR(AVERAGEIF(Loan_Data!$U$2:$U$801,$A4,Loan_Data!$W$2:$W$801),0) -> 11.44561 | K4: =IFERROR(AVERAGEIF(Loan_Data!$U$2:$U$801,$A4,Loan_Data!$X$2:$X$801),0) -> 43.463415 | L4: =IFERROR(AVERAGEIF(Loan_Data!$U$2:$U$801,$A4,Loan_Data!$AB$2:$AB$801),0) -> 22908.72 | M4: =IFERROR(AVERAGEIF(Loan_Data!$U$2:$U$801,$A4,Loan_Data!$AJ$2:$AJ$801),0) -> 0.44876992 | N4: =IFERROR(AVERAGEIF(Loan_Data!$U$2:$U$801,$A4,Loan_Data!$AI$2:$AI$801),0) -> 715.76423 | O4: =IFERROR(COUNTIFS(Loan_Data!$U$2:$U$801,$A4,Loan_Data!$AN$2:$AN$801,"Missed Payment")/(C4+F4),0) -> 0.17045455
A5: Education Loan | B5: =COUNTIF(Loan_Data!$U$2:$U$801,$A5) -> 96 | C5: =COUNTIFS(Loan_Data!$U$2:$U$801,$A5,Loan_Data!$AO$2:$AO$801,"Approved") -> 59 | D5: =COUNTIFS(Loan_Data!$U$2:$U$801,$A5,Loan_Data!$AO$2:$AO$801,"Rejected") -> 16 | E5: =COUNTIFS(Loan_Data!$U$2:$U$801,$A5,Loan_Data!$AO$2:$AO$801,"Pending") -> 17 | F5: =COUNTIFS(Loan_Data!$U$2:$U$801,$A5,Loan_Data!$AO$2:$AO$801,"Closed") -> 4 | G5: =IFERROR((C5+F5)/B5,0) -> 0.65625 | H5: =SUMIFS(Loan_Data!$V$2:$V$801,Loan_Data!$U$2:$U$801,$A5,Loan_Data!$AO$2:$AO$801,"Approved")+SUMIFS(Loan_Data!$V$2:$V$801,Loan_Data!$U$2:$U$801,$A5,Loan_Data!$AO$2:$AO$801,"Closed") -> 48619635 | I5: =IFERROR(H5/(C5+F5),0) -> 771740.24 | J5: =IFERROR(AVERAGEIF(Loan_Data!$U$2:$U$801,$A5,Loan_Data!$W$2:$W$801),0) -> 9.1025 | K5: =IFERROR(AVERAGEIF(Loan_Data!$U$2:$U$801,$A5,Loan_Data!$X$2:$X$801),0) -> 47.3125 | L5: =IFERROR(AVERAGEIF(Loan_Data!$U$2:$U$801,$A5,Loan_Data!$AB$2:$AB$801),0) -> 21990.886 | M5: =IFERROR(AVERAGEIF(Loan_Data!$U$2:$U$801,$A5,Loan_Data!$AJ$2:$AJ$801),0) -> 0.50934167 | N5: =IFERROR(AVERAGEIF(Loan_Data!$U$2:$U$801,$A5,Loan_Data!$AI$2:$AI$801),0) -> 711.22917 | O5: =IFERROR(COUNTIFS(Loan_Data!$U$2:$U$801,$A5,Loan_Data!$AN$2:$AN$801,"Missed Payment")/(C5+F5),0) -> 0.031746032
A6: Home Loan | B6: =COUNTIF(Loan_Data!$U$2:$U$801,$A6) -> 88 | C6: =COUNTIFS(Loan_Data!$U$2:$U$801,$A6,Loan_Data!$AO$2:$AO$801,"Approved") -> 50 | D6: =COUNTIFS(Loan_Data!$U$2:$U$801,$A6,Loan_Data!$AO$2:$AO$801,"Rejected") -> 16 | E6: =COUNTIFS(Loan_Data!$U$2:$U$801,$A6,Loan_Data!$AO$2:$AO$801,"Pending") -> 18 | F6: =COUNTIFS(Loan_Data!$U$2:$U$801,$A6,Loan_Data!$AO$2:$AO$801,"Closed") -> 4 | G6: =IFERROR((C6+F6)/B6,0) -> 0.61363636 | H6: =SUMIFS(Loan_Data!$V$2:$V$801,Loan_Data!$U$2:$U$801,$A6,Loan_Data!$AO$2:$AO$801,"Approved")+SUMIFS(Loan_Data!$V$2:$V$801,Loan_Data!$U$2:$U$801,$A6,Loan_Data!$AO$2:$AO$801,"Closed") -> 103104000 | I6: =IFERROR(H6/(C6+F6),0) -> 1909333.3 | J6: =IFERROR(AVERAGEIF(Loan_Data!$U$2:$U$801,$A6,Loan_Data!$W$2:$W$801),0) -> 10.064432 | K6: =IFERROR(AVERAGEIF(Loan_Data!$U$2:$U$801,$A6,Loan_Data!$X$2:$X$801),0) -> 182.79545 | L6: =IFERROR(AVERAGEIF(Loan_Data!$U$2:$U$801,$A6,Loan_Data!$AB$2:$AB$801),0) -> 21034.877 | M6: =IFERROR(AVERAGEIF(Loan_Data!$U$2:$U$801,$A6,Loan_Data!$AJ$2:$AJ$801),0) -> 0.3961125 | N6: =IFERROR(AVERAGEIF(Loan_Data!$U$2:$U$801,$A6,Loan_Data!$AI$2:$AI$801),0) -> 726.36364 | O6: =IFERROR(COUNTIFS(Loan_Data!$U$2:$U$801,$A6,Loan_Data!$AN$2:$AN$801,"Missed Payment")/(C6+F6),0) -> 0.14814815
A7: Personal Loan | B7: =COUNTIF(Loan_Data!$U$2:$U$801,$A7) -> 93 | C7: =COUNTIFS(Loan_Data!$U$2:$U$801,$A7,Loan_Data!$AO$2:$AO$801,"Approved") -> 61 | D7: =COUNTIFS(Loan_Data!$U$2:$U$801,$A7,Loan_Data!$AO$2:$AO$801,"Rejected") -> 14 | E7: =COUNTIFS(Loan_Data!$U$2:$U$801,$A7,Loan_Data!$AO$2:$AO$801,"Pending") -> 9 | F7: =COUNTIFS(Loan_Data!$U$2:$U$801,$A7,Loan_Data!$AO$2:$AO$801,"Closed") -> 9 | G7: =IFERROR((C7+F7)/B7,0) -> 0.75268817 | H7: =SUMIFS(Loan_Data!$V$2:$V$801,Loan_Data!$U$2:$U$801,$A7,Loan_Data!$AO$2:$AO$801,"Approved")+SUMIFS(Loan_Data!$V$2:$V$801,Loan_Data!$U$2:$U$801,$A7,Loan_Data!$AO$2:$AO$801,"Closed") -> 38829000 | I7: =IFERROR(H7/(C7+F7),0) -> 554700 | J7: =IFERROR(AVERAGEIF(Loan_Data!$U$2:$U$801,$A7,Loan_Data!$W$2:$W$801),0) -> 13.686344 | K7: =IFERROR(AVERAGEIF(Loan_Data!$U$2:$U$801,$A7,Loan_Data!$X$2:$X$801),0) -> 35.419355 | L7: =IFERROR(AVERAGEIF(Loan_Data!$U$2:$U$801,$A7,Loan_Data!$AB$2:$AB$801),0) -> 20662.786 | M7: =IFERROR(AVERAGEIF(Loan_Data!$U$2:$U$801,$A7,Loan_Data!$AJ$2:$AJ$801),0) -> 0.3351957 | N7: =IFERROR(AVERAGEIF(Loan_Data!$U$2:$U$801,$A7,Loan_Data!$AI$2:$AI$801),0) -> 718.29032 | O7: =IFERROR(COUNTIFS(Loan_Data!$U$2:$U$801,$A7,Loan_Data!$AN$2:$AN$801,"Missed Payment")/(C7+F7),0) -> 0.085714286
A8: SME Loan | B8: =COUNTIF(Loan_Data!$U$2:$U$801,$A8) -> 124 | C8: =COUNTIFS(Loan_Data!$U$2:$U$801,$A8,Loan_Data!$AO$2:$AO$801,"Approved") -> 77 | D8: =COUNTIFS(Loan_Data!$U$2:$U$801,$A8,Loan_Data!$AO$2:$AO$801,"Rejected") -> 23 | E8: =COUNTIFS(Loan_Data!$U$2:$U$801,$A8,Loan_Data!$AO$2:$AO$801,"Pending") -> 16 | F8: =COUNTIFS(Loan_Data!$U$2:$U$801,$A8,Loan_Data!$AO$2:$AO$801,"Closed") -> 8 | G8: =IFERROR((C8+F8)/B8,0) -> 0.68548387 | H8: =SUMIFS(Loan_Data!$V$2:$V$801,Loan_Data!$U$2:$U$801,$A8,Loan_Data!$AO$2:$AO$801,"Approved")+SUMIFS(Loan_Data!$V$2:$V$801,Loan_Data!$U$2:$U$801,$A8,Loan_Data!$AO$2:$AO$801,"Closed") -> 60999325 | I8: =IFERROR(H8/(C8+F8),0) -> 717639.12 | J8: =IFERROR(AVERAGEIF(Loan_Data!$U$2:$U$801,$A8,Loan_Data!$W$2:$W$801),0) -> 12.459194 | K8: =IFERROR(AVERAGEIF(Loan_Data!$U$2:$U$801,$A8,Loan_Data!$X$2:$X$801),0) -> 44.709677 | L8: =IFERROR(AVERAGEIF(Loan_Data!$U$2:$U$801,$A8,Loan_Data!$AB$2:$AB$801),0) -> 21058.642 | M8: =IFERROR(AVERAGEIF(Loan_Data!$U$2:$U$801,$A8,Loan_Data!$AJ$2:$AJ$801),0) -> 0.4049871 | N8: =IFERROR(AVERAGEIF(Loan_Data!$U$2:$U$801,$A8,Loan_Data!$AI$2:$AI$801),0) -> 720.57258 | O8: =IFERROR(COUNTIFS(Loan_Data!$U$2:$U$801,$A8,Loan_Data!$AN$2:$AN$801,"Missed Payment")/(C8+F8),0) -> 0.082352941
A9: TOTAL / OVERALL | B9: =SUM(B2:B8) -> 800 | C9: =SUM(C2:C8) -> 480 | D9: =SUM(D2:D8) -> 134 | E9: =SUM(E2:E8) -> 126 | F9: =SUM(F2:F8) -> 60 | G9: =IFERROR((C9+F9)/B9,0) -> 0.675 | H9: =SUM(H2:H8) -> 416564462 | I9: =IFERROR(H9/(C9+F9),0) -> 771415.67 | J9: =AVERAGE(J2:J8) -> 11.381472 | K9: =AVERAGE(K2:K8) -> 60.571575 | L9: =AVERAGE(L2:L8) -> 21271.586 | M9: =AVERAGE(M2:M8) -> 0.42931399 | N9: =AVERAGE(N2:N8) -> 716.35635 | O9: =IFERROR(SUMPRODUCT(O2:O8,(C2:C8+F2:F8))/(C9+F9),0) -> 0.094444444

Sheet Risk_Analysis
A1: Risk_Level | B1: Total_Count | C1: Pct_of_Total | D1: Approved_Count | E1: Rejected_Count | F1: Pending_Count | G1: Closed_Count | H1: Approval_Rate | I1: Total_Loan_Amount_Disbursed | J1: Average_Loan_Amount | K1: Average_Credit_Score | L1: Average_Interest_Rate | M1: Average_DTI | N1: Average_Default_Probability | O1: Missed_Payment_Rate | P1: Previous_Default_Rate
A2: Low | B2: =COUNTIF(Loan_Data!$AK$2:$AK$801,$A2) -> 164 | C2: =IFERROR(B2/COUNTA(Loan_Data!$AK$2:$AK$801),0) -> 0.205 | D2: =COUNTIFS(Loan_Data!$AK$2:$AK$801,$A2,Loan_Data!$AO$2:$AO$801,"Approved") -> 110 | E2: =COUNTIFS(Loan_Data!$AK$2:$AK$801,$A2,Loan_Data!$AO$2:$AO$801,"Rejected") -> 9 | F2: =COUNTIFS(Loan_Data!$AK$2:$AK$801,$A2,Loan_Data!$AO$2:$AO$801,"Pending") -> 26 | G2: =COUNTIFS(Loan_Data!$AK$2:$AK$801,$A2,Loan_Data!$AO$2:$AO$801,"Closed") -> 19 | H2: =IFERROR((D2+G2)/B2,0) -> 0.78658537 | I2: =SUMIFS(Loan_Data!$V$2:$V$801,Loan_Data!$AK$2:$AK$801,$A2,Loan_Data!$AO$2:$AO$801,"Approved")+SUMIFS(Loan_Data!$V$2:$V$801,Loan_Data!$AK$2:$AK$801,$A2,Loan_Data!$AO$2:$AO$801,"Closed") -> 94401000 | J2: =IFERROR(I2/(D2+G2),0) -> 731790.7 | K2: =IFERROR(AVERAGEIF(Loan_Data!$AK$2:$AK$801,$A2,Loan_Data!$AI$2:$AI$801),0) -> 817.5122 | L2: =IFERROR(AVERAGEIF(Loan_Data!$AK$2:$AK$801,$A2,Loan_Data!$W$2:$W$801),0) -> 11.041524 | M2: =IFERROR(AVERAGEIF(Loan_Data!$AK$2:$AK$801,$A2,Loan_Data!$AJ$2:$AJ$801),0) -> 0.25651037 | N2: =IFERROR(AVERAGEIF(Loan_Data!$AK$2:$AK$801,$A2,Loan_Data!$AP$2:$AP$801),0) -> 0.13630488 | O2: =IFERROR(COUNTIFS(Loan_Data!$AK$2:$AK$801,$A2,Loan_Data!$AN$2:$AN$801,"Missed Payment")/(D2+G2),0) -> 0.023255814 | P2: =IFERROR(COUNTIFS(Loan_Data!$AK$2:$AK$801,$A2,Loan_Data!$AM$2:$AM$801,"Yes")/B2,0) -> 0.10365854
A3: Medium | B3: =COUNTIF(Loan_Data!$AK$2:$AK$801,$A3) -> 456 | C3: =IFERROR(B3/COUNTA(Loan_Data!$AK$2:$AK$801),0) -> 0.57 | D3: =COUNTIFS(Loan_Data!$AK$2:$AK$801,$A3,Loan_Data!$AO$2:$AO$801,"Approved") -> 278 | E3: =COUNTIFS(Loan_Data!$AK$2:$AK$801,$A3,Loan_Data!$AO$2:$AO$801,"Rejected") -> 77 | F3: =COUNTIFS(Loan_Data!$AK$2:$AK$801,$A3,Loan_Data!$AO$2:$AO$801,"Pending") -> 73 | G3: =COUNTIFS(Loan_Data!$AK$2:$AK$801,$A3,Loan_Data!$AO$2:$AO$801,"Closed") -> 28 | H3: =IFERROR((D3+G3)/B3,0) -> 0.67105263 | I3: =SUMIFS(Loan_Data!$V$2:$V$801,Loan_Data!$AK$2:$AK$801,$A3,Loan_Data!$AO$2:$AO$801,"Approved")+SUMIFS(Loan_Data!$V$2:$V$801,Loan_Data!$AK$2:$AK$801,$A3,Loan_Data!$AO$2:$AO$801,"Closed") -> 236567000 | J3: =IFERROR(I3/(D3+G3),0) -> 773094.77 | K3: =IFERROR(AVERAGEIF(Loan_Data!$AK$2:$AK$801,$A3,Loan_Data!$AI$2:$AI$801),0) -> 706.70833 | L3: =IFERROR(AVERAGEIF(Loan_Data!$AK$2:$AK$801,$A3,Loan_Data!$W$2:$W$801),0) -> 11.324342 | M3: =IFERROR(AVERAGEIF(Loan_Data!$AK$2:$AK$801,$A3,Loan_Data!$AJ$2:$AJ$801),0) -> 0.3425 | N3: =IFERROR(AVERAGEIF(Loan_Data!$AK$2:$AK$801,$A3,Loan_Data!$AP$2:$AP$801),0) -> 0.25341886 | O3: =IFERROR(COUNTIFS(Loan_Data!$AK$2:$AK$801,$A3,Loan_Data!$AN$2:$AN$801,"Missed Payment")/(D3+G3),0) -> 0.075163399 | P3: =IFERROR(COUNTIFS(Loan_Data!$AK$2:$AK$801,$A3,Loan_Data!$AM$2:$AM$801,"Yes")/B3,0) -> 0.15570175
A4: High | B4: =COUNTIF(Loan_Data!$AK$2:$AK$801,$A4) -> 180 | C4: =IFERROR(B4/COUNTA(Loan_Data!$AK$2:$AK$801),0) -> 0.225 | D4: =COUNTIFS(Loan_Data!$AK$2:$AK$801,$A4,Loan_Data!$AO$2:$AO$801,"Approved") -> 92 | E4: =COUNTIFS(Loan_Data!$AK$2:$AK$801,$A4,Loan_Data!$AO$2:$AO$801,"Rejected") -> 48 | F4: =COUNTIFS(Loan_Data!$AK$2:$AK$801,$A4,Loan_Data!$AO$2:$AO$801,"Pending") -> 27 | G4: =COUNTIFS(Loan_Data!$AK$2:$AK$801,$A4,Loan_Data!$AO$2:$AO$801,"Closed") -> 13 | H4: =IFERROR((D4+G4)/B4,0) -> 0.58333333 | I4: =SUMIFS(Loan_Data!$V$2:$V$801,Loan_Data!$AK$2:$AK$801,$A4,Loan_Data!$AO$2:$AO$801,"Approved")+SUMIFS(Loan_Data!$V$2:$V$801,Loan_Data!$AK$2:$AK$801,$A4,Loan_Data!$AO$2:$AO$801,"Closed") -> 85596462 | J4: =IFERROR(I4/(D4+G4),0) -> 815204.4 | K4: =IFERROR(AVERAGEIF(Loan_Data!$AK$2:$AK$801,$A4,Loan_Data!$AI$2:$AI$801),0) -> 648.09444 | L4: =IFERROR(AVERAGEIF(Loan_Data!$AK$2:$AK$801,$A4,Loan_Data!$W$2:$W$801),0) -> 11.428667 | M4: =IFERROR(AVERAGEIF(Loan_Data!$AK$2:$AK$801,$A4,Loan_Data!$AJ$2:$AJ$801),0) -> 0.83909611 | N4: =IFERROR(AVERAGEIF(Loan_Data!$AK$2:$AK$801,$A4,Loan_Data!$AP$2:$AP$801),0) -> 0.31132222 | O4: =IFERROR(COUNTIFS(Loan_Data!$AK$2:$AK$801,$A4,Loan_Data!$AN$2:$AN$801,"Missed Payment")/(D4+G4),0) -> 0.23809524 | P4: =IFERROR(COUNTIFS(Loan_Data!$AK$2:$AK$801,$A4,Loan_Data!$AM$2:$AM$801,"Yes")/B4,0) -> 0.15555556
A5: TOTAL / OVERALL | B5: =SUM(B2:B4) -> 800 | C5: =SUM(C2:C4) -> 1 | D5: =SUM(D2:D4) -> 480 | E5: =SUM(E2:E4) -> 134 | F5: =SUM(F2:F4) -> 126 | G5: =SUM(G2:G4) -> 60 | H5: =IFERROR((D5+G5)/B5,0) -> 0.675 | I5: =SUM(I2:I4) -> 416564462 | J5: =IFERROR(I5/(D5+G5),0) -> 771415.67 | K5: =AVERAGE(Loan_Data!$AI$2:$AI$801) -> 716.235 | L5: =AVERAGE(Loan_Data!$W$2:$W$801) -> 11.289838 | M5: =AVERAGE(Loan_Data!$AJ$2:$AJ$801) -> 0.43660625 | N5: =AVERAGE(Loan_Data!$AP$2:$AP$801) -> 0.24243875 | O5: =IFERROR(SUMPRODUCT(O2:O4,(D2:D4+G2:G4))/(D5+G5),0) -> 0.094444444 | P5: =COUNTIF(Loan_Data!$AM$2:$AM$801,"Yes")/COUNTA(Loan_Data!$AK$2:$AK$801) -> 0.145
